{
"meta":{"test_sets":[],"test_metrics":[],"learn_metrics":[{"best_value":"Min","name":"RMSE"}],"launch_mode":"Train","parameters":"","iteration_count":1000,"learn_sets":["learn"],"name":"experiment"},
"iterations":[
{"learn":[14.59871775],"iteration":0,"passed_time":0.2055312338,"remaining_time":205.3257026},
{"learn":[14.22518863],"iteration":1,"passed_time":0.2067047163,"remaining_time":103.1456535},
{"learn":[13.8866124],"iteration":2,"passed_time":0.2076534753,"remaining_time":69.01017163},
{"learn":[13.52356875],"iteration":3,"passed_time":0.2086527374,"remaining_time":51.9545316},
{"learn":[13.18870211],"iteration":4,"passed_time":0.2097521286,"remaining_time":41.74067359},
{"learn":[12.9124226],"iteration":5,"passed_time":0.2107839614,"remaining_time":34.91987626},
{"learn":[12.60003351],"iteration":6,"passed_time":0.2119118841,"remaining_time":30.06121441},
{"learn":[12.32990573],"iteration":7,"passed_time":0.2129301403,"remaining_time":26.4033374},
{"learn":[12.0660619],"iteration":8,"passed_time":0.2139761285,"remaining_time":23.56114926},
{"learn":[11.77309809],"iteration":9,"passed_time":0.2151622091,"remaining_time":21.3010587},
{"learn":[11.49227636],"iteration":10,"passed_time":0.2173207776,"remaining_time":19.53911355},
{"learn":[11.26264833],"iteration":11,"passed_time":0.2183768327,"remaining_time":17.97969256},
{"learn":[11.04260393],"iteration":12,"passed_time":0.2194132158,"remaining_time":16.65852646},
{"learn":[10.79916926],"iteration":13,"passed_time":0.2203411604,"remaining_time":15.51831316},
{"learn":[10.5541002],"iteration":14,"passed_time":0.2214280591,"remaining_time":14.54044255},
{"learn":[10.31918115],"iteration":15,"passed_time":0.2223930821,"remaining_time":13.67717455},
{"learn":[10.10004441],"iteration":16,"passed_time":0.2233573829,"remaining_time":12.9153122},
{"learn":[9.894556723],"iteration":17,"passed_time":0.224427696,"remaining_time":12.24377764},
{"learn":[9.690174082],"iteration":18,"passed_time":0.2254098156,"remaining_time":11.63826469},
{"learn":[9.506034866],"iteration":19,"passed_time":0.2263960584,"remaining_time":11.09340686},
{"learn":[9.338524633],"iteration":20,"passed_time":0.2273674965,"remaining_time":10.59965615},
{"learn":[9.170203312],"iteration":21,"passed_time":0.2284568093,"remaining_time":10.15594361},
{"learn":[9.010299969],"iteration":22,"passed_time":0.2297494464,"remaining_time":9.759356917},
{"learn":[8.843866678],"iteration":23,"passed_time":0.2315471291,"remaining_time":9.416249915},
{"learn":[8.690548059],"iteration":24,"passed_time":0.232734166,"remaining_time":9.076632474},
{"learn":[8.555307687],"iteration":25,"passed_time":0.2337662425,"remaining_time":8.757243083},
{"learn":[8.413851302],"iteration":26,"passed_time":0.2347657588,"remaining_time":8.460262343},
{"learn":[8.29256019],"iteration":27,"passed_time":0.2359486725,"remaining_time":8.190789632},
{"learn":[8.162193833],"iteration":28,"passed_time":0.2369569598,"remaining_time":7.933972688},
{"learn":[8.040736294],"iteration":29,"passed_time":0.2379497434,"remaining_time":7.693708369},
{"learn":[7.921220278],"iteration":30,"passed_time":0.2388345419,"remaining_time":7.465505518},
{"learn":[7.809589039],"iteration":31,"passed_time":0.239775645,"remaining_time":7.25321326},
{"learn":[7.699675801],"iteration":32,"passed_time":0.240763135,"remaining_time":7.055089441},
{"learn":[7.60645267],"iteration":33,"passed_time":0.2417951693,"remaining_time":6.869827456},
{"learn":[7.498880302],"iteration":34,"passed_time":0.2428653763,"remaining_time":6.696145375},
{"learn":[7.401158744],"iteration":35,"passed_time":0.2440394342,"remaining_time":6.534833738},
{"learn":[7.306431077],"iteration":36,"passed_time":0.2459642449,"remaining_time":6.40171805},
{"learn":[7.223863468],"iteration":37,"passed_time":0.247183147,"remaining_time":6.257636511},
{"learn":[7.143477682],"iteration":38,"passed_time":0.2481729928,"remaining_time":6.11523708},
{"learn":[7.062817131],"iteration":39,"passed_time":0.2491403797,"remaining_time":5.979369112},
{"learn":[6.990793435],"iteration":40,"passed_time":0.2501734004,"remaining_time":5.851616852},
{"learn":[6.931862224],"iteration":41,"passed_time":0.2511467892,"remaining_time":5.728538669},
{"learn":[6.858296558],"iteration":42,"passed_time":0.2522361764,"remaining_time":5.613721414},
{"learn":[6.786268161],"iteration":43,"passed_time":0.2532228931,"remaining_time":5.501842858},
{"learn":[6.717118549],"iteration":44,"passed_time":0.2542678933,"remaining_time":5.396129735},
{"learn":[6.652948106],"iteration":45,"passed_time":0.2552258217,"remaining_time":5.293161606},
{"learn":[6.589686076],"iteration":46,"passed_time":0.2562262677,"remaining_time":5.195396449},
{"learn":[6.531283097],"iteration":47,"passed_time":0.2575788426,"remaining_time":5.108647044},
{"learn":[6.471368031],"iteration":48,"passed_time":0.2590361447,"remaining_time":5.027415788},
{"learn":[6.416481395],"iteration":49,"passed_time":0.2611644938,"remaining_time":4.962125382},
{"learn":[6.369870822],"iteration":50,"passed_time":0.2621855088,"remaining_time":4.878706821},
{"learn":[6.325678067],"iteration":51,"passed_time":0.2633435535,"remaining_time":4.800955552},
{"learn":[6.275766122],"iteration":52,"passed_time":0.2644679345,"remaining_time":4.725493093},
{"learn":[6.224773967],"iteration":53,"passed_time":0.2657561705,"remaining_time":4.655654394},
{"learn":[6.182249254],"iteration":54,"passed_time":0.266738677,"remaining_time":4.583055451},
{"learn":[6.139904173],"iteration":55,"passed_time":0.267686143,"remaining_time":4.512423554},
{"learn":[6.100525536],"iteration":56,"passed_time":0.2686257351,"remaining_time":4.44410646},
{"learn":[6.062568564],"iteration":57,"passed_time":0.2696032542,"remaining_time":4.378728714},
{"learn":[6.030559288],"iteration":58,"passed_time":0.2710657881,"remaining_time":4.323269603},
{"learn":[5.997931376],"iteration":59,"passed_time":0.2726768853,"remaining_time":4.27193787},
{"learn":[5.964103835],"iteration":60,"passed_time":0.2746767059,"remaining_time":4.228220112},
{"learn":[5.933729724],"iteration":61,"passed_time":0.2756168477,"remaining_time":4.16981618},
{"learn":[5.901932711],"iteration":62,"passed_time":0.2766725254,"remaining_time":4.114954862},
{"learn":[5.873727795],"iteration":63,"passed_time":0.2776049767,"remaining_time":4.059972784},
{"learn":[5.846485734],"iteration":64,"passed_time":0.2785209222,"remaining_time":4.006416343},
{"learn":[5.820630862],"iteration":65,"passed_time":0.2793935874,"remaining_time":3.953842586},
{"learn":[5.793646238],"iteration":66,"passed_time":0.280331979,"remaining_time":3.903727409},
{"learn":[5.765388646],"iteration":67,"passed_time":0.2812605825,"remaining_time":3.854924454},
{"learn":[5.747073912],"iteration":68,"passed_time":0.2822936192,"remaining_time":3.808918254},
{"learn":[5.722315217],"iteration":69,"passed_time":0.2832025386,"remaining_time":3.762548013},
{"learn":[5.699970599],"iteration":70,"passed_time":0.2841221189,"remaining_time":3.717597865},
{"learn":[5.682732647],"iteration":71,"passed_time":0.2852601794,"remaining_time":3.676686756},
{"learn":[5.663525791],"iteration":72,"passed_time":0.2864856016,"remaining_time":3.637974695},
{"learn":[5.642381613],"iteration":73,"passed_time":0.2878798905,"remaining_time":3.602388901},
{"learn":[5.621404779],"iteration":74,"passed_time":0.289218109,"remaining_time":3.567023344},
{"learn":[5.602460129],"iteration":75,"passed_time":0.2900948104,"remaining_time":3.526942169},
{"learn":[5.587337574],"iteration":76,"passed_time":0.2909949342,"remaining_time":3.488160055},
{"learn":[5.572393026],"iteration":77,"passed_time":0.291870319,"remaining_time":3.450056848},
{"learn":[5.558425806],"iteration":78,"passed_time":0.2928065824,"remaining_time":3.413605853},
{"learn":[5.541518902],"iteration":79,"passed_time":0.2938899594,"remaining_time":3.379734533},
{"learn":[5.526157283],"iteration":80,"passed_time":0.2953177326,"remaining_time":3.350580201},
{"learn":[5.511746977],"iteration":81,"passed_time":0.2963672741,"remaining_time":3.317867776},
{"learn":[5.504975022],"iteration":82,"passed_time":0.2969983824,"remaining_time":3.281295381},
{"learn":[5.493980522],"iteration":83,"passed_time":0.2980368267,"remaining_time":3.250020635},
{"learn":[5.480745463],"iteration":84,"passed_time":0.2991950799,"remaining_time":3.220747037},
{"learn":[5.464052013],"iteration":85,"passed_time":0.300445408,"remaining_time":3.193105848},
{"learn":[5.449143727],"iteration":86,"passed_time":0.3019472699,"remaining_time":3.168711005},
{"learn":[5.438255432],"iteration":87,"passed_time":0.3042753865,"remaining_time":3.15339946},
{"learn":[5.425927931],"iteration":88,"passed_time":0.3052901598,"remaining_time":3.124936355},
{"learn":[5.412331217],"iteration":89,"passed_time":0.3061719326,"remaining_time":3.09573843},
{"learn":[5.400691499],"iteration":90,"passed_time":0.3070901897,"remaining_time":3.06752728},
{"learn":[5.391618744],"iteration":91,"passed_time":0.3079931156,"remaining_time":3.039758141},
{"learn":[5.380766572],"iteration":92,"passed_time":0.3088528037,"remaining_time":3.012145086},
{"learn":[5.372207183],"iteration":93,"passed_time":0.309748437,"remaining_time":2.985447701},
{"learn":[5.362918837],"iteration":94,"passed_time":0.3106777204,"remaining_time":2.959614073},
{"learn":[5.348292324],"iteration":95,"passed_time":0.3116194527,"remaining_time":2.934416513},
{"learn":[5.339772295],"iteration":96,"passed_time":0.3124124125,"remaining_time":2.908334108},
{"learn":[5.331515983],"iteration":97,"passed_time":0.3132409586,"remaining_time":2.883095354},
{"learn":[5.323861644],"iteration":98,"passed_time":0.314110764,"remaining_time":2.858725236},
{"learn":[5.313277281],"iteration":99,"passed_time":0.3151624391,"remaining_time":2.836461952},
{"learn":[5.30685627],"iteration":100,"passed_time":0.3164759247,"remaining_time":2.816949072},
{"learn":[5.29652059],"iteration":101,"passed_time":0.3176894724,"remaining_time":2.796913198},
{"learn":[5.288350766],"iteration":102,"passed_time":0.3192820062,"remaining_time":2.780543297},
{"learn":[5.27993346],"iteration":103,"passed_time":0.3203237511,"remaining_time":2.759712317},
{"learn":[5.271789139],"iteration":104,"passed_time":0.3211950193,"remaining_time":2.737805164},
{"learn":[5.262684686],"iteration":105,"passed_time":0.3220101934,"remaining_time":2.71582182},
{"learn":[5.251619772],"iteration":106,"passed_time":0.3231736994,"remaining_time":2.697141249},
{"learn":[5.241012171],"iteration":107,"passed_time":0.3241418139,"remaining_time":2.677171278},
{"learn":[5.232684032],"iteration":108,"passed_time":0.3250687681,"remaining_time":2.657213508},
{"learn":[5.224267141],"iteration":109,"passed_time":0.3258593972,"remaining_time":2.63649876},
{"learn":[5.216324968],"iteration":110,"passed_time":0.3266094063,"remaining_time":2.615817678},
{"learn":[5.211102527],"iteration":111,"passed_time":0.3273616109,"remaining_time":2.595509915},
{"learn":[5.206364257],"iteration":112,"passed_time":0.32811011,"remaining_time":2.575519182},
{"learn":[5.196937641],"iteration":113,"passed_time":0.32894362,"remaining_time":2.556526731},
{"learn":[5.190746047],"iteration":114,"passed_time":0.3300326533,"remaining_time":2.539816506},
{"learn":[5.181885213],"iteration":115,"passed_time":0.3311533719,"remaining_time":2.523617076},
{"learn":[5.178293568],"iteration":116,"passed_time":0.3319719446,"remaining_time":2.505395103},
{"learn":[5.170991438],"iteration":117,"passed_time":0.3335008505,"remaining_time":2.492777544},
{"learn":[5.166257212],"iteration":118,"passed_time":0.3343939974,"remaining_time":2.475639594},
{"learn":[5.161421246],"iteration":119,"passed_time":0.3351838823,"remaining_time":2.458015137},
{"learn":[5.158223542],"iteration":120,"passed_time":0.3359616977,"remaining_time":2.440581258},
{"learn":[5.15470988],"iteration":121,"passed_time":0.3365844763,"remaining_time":2.422304673},
{"learn":[5.146388143],"iteration":122,"passed_time":0.3373536338,"remaining_time":2.405358836},
{"learn":[5.139529364],"iteration":123,"passed_time":0.3381156415,"remaining_time":2.388623403},
{"learn":[5.134276023],"iteration":124,"passed_time":0.3390095557,"remaining_time":2.37306689},
{"learn":[5.128536065],"iteration":125,"passed_time":0.3400159279,"remaining_time":2.358523182},
{"learn":[5.123300353],"iteration":126,"passed_time":0.3406982362,"remaining_time":2.341965041},
{"learn":[5.116200518],"iteration":127,"passed_time":0.3416188436,"remaining_time":2.327278372},
{"learn":[5.108728704],"iteration":128,"passed_time":0.342589637,"remaining_time":2.313143983},
{"learn":[5.104075866],"iteration":129,"passed_time":0.3435529238,"remaining_time":2.299161875},
{"learn":[5.100317606],"iteration":130,"passed_time":0.3445932401,"remaining_time":2.285889508},
{"learn":[5.095814182],"iteration":131,"passed_time":0.3459032723,"remaining_time":2.274576063},
{"learn":[5.092146915],"iteration":132,"passed_time":0.3475059504,"remaining_time":2.265320744},
{"learn":[5.085258329],"iteration":133,"passed_time":0.3484506008,"remaining_time":2.251927017},
{"learn":[5.079219421],"iteration":134,"passed_time":0.3492370158,"remaining_time":2.237703842},
{"learn":[5.076476829],"iteration":135,"passed_time":0.3500220112,"remaining_time":2.223669247},
{"learn":[5.072133867],"iteration":136,"passed_time":0.3507724343,"remaining_time":2.209610298},
{"learn":[5.067031564],"iteration":137,"passed_time":0.3515236203,"remaining_time":2.195748991},
{"learn":[5.061358312],"iteration":138,"passed_time":0.3523747898,"remaining_time":2.182695641},
{"learn":[5.056759124],"iteration":139,"passed_time":0.3531562902,"remaining_time":2.16938864},
{"learn":[5.050254],"iteration":140,"passed_time":0.3539205789,"remaining_time":2.156154449},
{"learn":[5.048376474],"iteration":141,"passed_time":0.3544418986,"remaining_time":2.14162781},
{"learn":[5.042603751],"iteration":142,"passed_time":0.355202455,"remaining_time":2.128730797},
{"learn":[5.037477349],"iteration":143,"passed_time":0.3559716588,"remaining_time":2.116053749},
{"learn":[5.03230489],"iteration":144,"passed_time":0.3567269177,"remaining_time":2.103458722},
{"learn":[5.025976187],"iteration":145,"passed_time":0.3574894772,"remaining_time":2.091068586},
{"learn":[5.01952451],"iteration":146,"passed_time":0.358336228,"remaining_time":2.079325187},
{"learn":[5.017569424],"iteration":147,"passed_time":0.3592932343,"remaining_time":2.068363754},
{"learn":[5.008962367],"iteration":148,"passed_time":0.3603479055,"remaining_time":2.058094413},
{"learn":[5.003880266],"iteration":149,"passed_time":0.3617726063,"remaining_time":2.050044769},
{"learn":[4.996387564],"iteration":150,"passed_time":0.3627337498,"remaining_time":2.039476514},
{"learn":[4.993361683],"iteration":151,"passed_time":0.3635039908,"remaining_time":2.027969633},
{"learn":[4.99005752],"iteration":152,"passed_time":0.3642743182,"remaining_time":2.016603579},
{"learn":[4.986908764],"iteration":153,"passed_time":0.3650045572,"remaining_time":2.005154905},
{"learn":[4.985207175],"iteration":154,"passed_time":0.3658560343,"remaining_time":1.994505477},
{"learn":[4.979003494],"iteration":155,"passed_time":0.3666700295,"remaining_time":1.983778877},
{"learn":[4.973142217],"iteration":156,"passed_time":0.3674488379,"remaining_time":1.97298962},
{"learn":[4.967056696],"iteration":157,"passed_time":0.3681997696,"remaining_time":1.962178519},
{"learn":[4.961460696],"iteration":158,"passed_time":0.368957332,"remaining_time":1.951529033},
{"learn":[4.954240363],"iteration":159,"passed_time":0.3697517703,"remaining_time":1.941196794},
{"learn":[4.952320707],"iteration":160,"passed_time":0.3702472902,"remaining_time":1.92942532},
{"learn":[4.948337777],"iteration":161,"passed_time":0.3710393555,"remaining_time":1.919327036},
{"learn":[4.943228639],"iteration":162,"passed_time":0.371753718,"remaining_time":1.908943938},
{"learn":[4.938545759],"iteration":163,"passed_time":0.3724997994,"remaining_time":1.898840441},
{"learn":[4.935330572],"iteration":164,"passed_time":0.3734397533,"remaining_time":1.889831479},
{"learn":[4.932051543],"iteration":165,"passed_time":0.3745060215,"remaining_time":1.881554349},
{"learn":[4.928964153],"iteration":166,"passed_time":0.3758342987,"remaining_time":1.874670484},
{"learn":[4.922860227],"iteration":167,"passed_time":0.3772831314,"remaining_time":1.868449794},
{"learn":[4.917668772],"iteration":168,"passed_time":0.3780593207,"remaining_time":1.85897808},
{"learn":[4.910365386],"iteration":169,"passed_time":0.3788269757,"remaining_time":1.849566999},
{"learn":[4.906457206],"iteration":170,"passed_time":0.3796003102,"remaining_time":1.840284545},
{"learn":[4.901996508],"iteration":171,"passed_time":0.3803678632,"remaining_time":1.831073202},
{"learn":[4.896816173],"iteration":172,"passed_time":0.3811204442,"remaining_time":1.821887904},
{"learn":[4.891123132],"iteration":173,"passed_time":0.3818719864,"remaining_time":1.812794602},
{"learn":[4.887630202],"iteration":174,"passed_time":0.3826337791,"remaining_time":1.803844958},
{"learn":[4.885259712],"iteration":175,"passed_time":0.3834136,"remaining_time":1.795072764},
{"learn":[4.880659728],"iteration":176,"passed_time":0.384177559,"remaining_time":1.786317125},
{"learn":[4.877299723],"iteration":177,"passed_time":0.3849647861,"remaining_time":1.777758731},
{"learn":[4.874038772],"iteration":178,"passed_time":0.3857235818,"remaining_time":1.769156763},
{"learn":[4.86943698],"iteration":179,"passed_time":0.386459253,"remaining_time":1.760536597},
{"learn":[4.861268711],"iteration":180,"passed_time":0.3872120576,"remaining_time":1.752081078},
{"learn":[4.858673056],"iteration":181,"passed_time":0.3880626859,"remaining_time":1.744149874},
{"learn":[4.854036207],"iteration":182,"passed_time":0.3891327959,"remaining_time":1.737275925},
{"learn":[4.85130244],"iteration":183,"passed_time":0.3902476331,"remaining_time":1.730663416},
{"learn":[4.847510084],"iteration":184,"passed_time":0.3918177093,"remaining_time":1.726115854},
{"learn":[4.845691673],"iteration":185,"passed_time":0.3926706487,"remaining_time":1.718461871},
{"learn":[4.842058646],"iteration":186,"passed_time":0.3936807354,"remaining_time":1.711563839},
{"learn":[4.838623675],"iteration":187,"passed_time":0.3948283101,"remaining_time":1.705322276},
{"learn":[4.834602161],"iteration":188,"passed_time":0.3958076941,"remaining_time":1.698412909},
{"learn":[4.830858976],"iteration":189,"passed_time":0.3967359408,"remaining_time":1.691347958},
{"learn":[4.827590511],"iteration":190,"passed_time":0.3975355192,"remaining_time":1.683802278},
{"learn":[4.822246226],"iteration":191,"passed_time":0.3983815474,"remaining_time":1.676522346},
{"learn":[4.816686395],"iteration":192,"passed_time":0.3991987814,"remaining_time":1.669188687},
{"learn":[4.814797121],"iteration":193,"passed_time":0.4000334371,"remaining_time":1.661994589},
{"learn":[4.811639392],"iteration":194,"passed_time":0.4008318849,"remaining_time":1.654716243},
{"learn":[4.804813432],"iteration":195,"passed_time":0.4017382334,"remaining_time":1.647946631},
{"learn":[4.80251613],"iteration":196,"passed_time":0.4025279711,"remaining_time":1.640761222},
{"learn":[4.800087884],"iteration":197,"passed_time":0.4035860549,"remaining_time":1.634727353},
{"learn":[4.794773135],"iteration":198,"passed_time":0.4046937894,"remaining_time":1.628943343},
{"learn":[4.791664833],"iteration":199,"passed_time":0.4061383648,"remaining_time":1.624553459},
{"learn":[4.785989873],"iteration":200,"passed_time":0.4071962209,"remaining_time":1.618655625},
{"learn":[4.782387142],"iteration":201,"passed_time":0.4080056211,"remaining_time":1.611824186},
{"learn":[4.778623704],"iteration":202,"passed_time":0.4088675385,"remaining_time":1.605258267},
{"learn":[4.775772178],"iteration":203,"passed_time":0.4097249934,"remaining_time":1.598730857},
{"learn":[4.77023101],"iteration":204,"passed_time":0.4107933834,"remaining_time":1.593076779},
{"learn":[4.764496689],"iteration":205,"passed_time":0.4116630872,"remaining_time":1.586701414},
{"learn":[4.763138716],"iteration":206,"passed_time":0.4124074952,"remaining_time":1.579899245},
{"learn":[4.758053283],"iteration":207,"passed_time":0.4131855564,"remaining_time":1.573283465},
{"learn":[4.755063788],"iteration":208,"passed_time":0.4139559999,"remaining_time":1.566694717},
{"learn":[4.752465267],"iteration":209,"passed_time":0.414734147,"remaining_time":1.560190362},
{"learn":[4.748067377],"iteration":210,"passed_time":0.4154837646,"remaining_time":1.553633603},
{"learn":[4.744163298],"iteration":211,"passed_time":0.4162319646,"remaining_time":1.547126359},
{"learn":[4.736670896],"iteration":212,"passed_time":0.4170300944,"remaining_time":1.540857673},
{"learn":[4.73349255],"iteration":213,"passed_time":0.4180276493,"remaining_time":1.535372581},
{"learn":[4.731864595],"iteration":214,"passed_time":0.4190203379,"remaining_time":1.529911466},
{"learn":[4.728398311],"iteration":215,"passed_time":0.4204082001,"remaining_time":1.52592606},
{"learn":[4.723865975],"iteration":216,"passed_time":0.421362816,"remaining_time":1.520401313},
{"learn":[4.723483365],"iteration":217,"passed_time":0.4221121411,"remaining_time":1.514182084},
{"learn":[4.72095416],"iteration":218,"passed_time":0.4228722217,"remaining_time":1.508051165},
{"learn":[4.716173382],"iteration":219,"passed_time":0.4236491165,"remaining_time":1.502028686},
{"learn":[4.710563974],"iteration":220,"passed_time":0.424412682,"remaining_time":1.496006694},
{"learn":[4.707160263],"iteration":221,"passed_time":0.4251651324,"remaining_time":1.489993122},
{"learn":[4.70408351],"iteration":222,"passed_time":0.4259240205,"remaining_time":1.484049165},
{"learn":[4.702501831],"iteration":223,"passed_time":0.4266828839,"remaining_time":1.478151419},
{"learn":[4.700269738],"iteration":224,"passed_time":0.4274396313,"remaining_time":1.472292063},
{"learn":[4.695346302],"iteration":225,"passed_time":0.4281989169,"remaining_time":1.466486556},
{"learn":[4.689769299],"iteration":226,"passed_time":0.4289549074,"remaining_time":1.460714288},
{"learn":[4.687919514],"iteration":227,"passed_time":0.4297596407,"remaining_time":1.455151064},
{"learn":[4.682982074],"iteration":228,"passed_time":0.4305453924,"remaining_time":1.449565492},
{"learn":[4.679578702],"iteration":229,"passed_time":0.4313241601,"remaining_time":1.443998275},
{"learn":[4.675751423],"iteration":230,"passed_time":0.4323083582,"remaining_time":1.439156396},
{"learn":[4.672710726],"iteration":231,"passed_time":0.4332793611,"remaining_time":1.434304092},
{"learn":[4.6690533],"iteration":232,"passed_time":0.4345107844,"remaining_time":1.430342368},
{"learn":[4.667595702],"iteration":233,"passed_time":0.4359756545,"remaining_time":1.427168168},
{"learn":[4.664241291],"iteration":234,"passed_time":0.4368711566,"remaining_time":1.422155042},
{"learn":[4.662246999],"iteration":235,"passed_time":0.4376987465,"remaining_time":1.416956959},
{"learn":[4.658668443],"iteration":236,"passed_time":0.4384494837,"remaining_time":1.411548338},
{"learn":[4.658017572],"iteration":237,"passed_time":0.4391525898,"remaining_time":1.406026359},
{"learn":[4.657656705],"iteration":238,"passed_time":0.4398519923,"remaining_time":1.400532913},
{"learn":[4.653242871],"iteration":239,"passed_time":0.4408009603,"remaining_time":1.395869708},
{"learn":[4.6507302],"iteration":240,"passed_time":0.4415487478,"remaining_time":1.390603733},
{"learn":[4.647671336],"iteration":241,"passed_time":0.4424039822,"remaining_time":1.385711647},
{"learn":[4.645506007],"iteration":242,"passed_time":0.4431369092,"remaining_time":1.380471771},
{"learn":[4.641297906],"iteration":243,"passed_time":0.4439012898,"remaining_time":1.375366291},
{"learn":[4.63798107],"iteration":244,"passed_time":0.4446256202,"remaining_time":1.37017283},
{"learn":[4.635062318],"iteration":245,"passed_time":0.4453586301,"remaining_time":1.365042305},
{"learn":[4.631606017],"iteration":246,"passed_time":0.4461345737,"remaining_time":1.360078275},
{"learn":[4.630215494],"iteration":247,"passed_time":0.4470077972,"remaining_time":1.355442998},
{"learn":[4.62729814],"iteration":248,"passed_time":0.4479874333,"remaining_time":1.351158885},
{"learn":[4.624691756],"iteration":249,"passed_time":0.4494801625,"remaining_time":1.348440488},
{"learn":[4.621840053],"iteration":250,"passed_time":0.4506853001,"remaining_time":1.344873665},
{"learn":[4.619602091],"iteration":251,"passed_time":0.4515267268,"remaining_time":1.340245999},
{"learn":[4.613584029],"iteration":252,"passed_time":0.4523383049,"remaining_time":1.335560133},
{"learn":[4.6119388],"iteration":253,"passed_time":0.4531743265,"remaining_time":1.330976565},
{"learn":[4.60870702],"iteration":254,"passed_time":0.454497082,"remaining_time":1.327844416},
{"learn":[4.604771557],"iteration":255,"passed_time":0.4555464481,"remaining_time":1.323931865},
{"learn":[4.604231277],"iteration":256,"passed_time":0.4563466481,"remaining_time":1.319321243},
{"learn":[4.600750354],"iteration":257,"passed_time":0.4571391657,"remaining_time":1.314718066},
{"learn":[4.596488253],"iteration":258,"passed_time":0.4579039936,"remaining_time":1.310065094},
{"learn":[4.59470784],"iteration":259,"passed_time":0.4587143064,"remaining_time":1.305571487},
{"learn":[4.588818005],"iteration":260,"passed_time":0.459479987,"remaining_time":1.300979733},
{"learn":[4.585054174],"iteration":261,"passed_time":0.4602609512,"remaining_time":1.296460237},
{"learn":[4.581471435],"iteration":262,"passed_time":0.4610083854,"remaining_time":1.291875209},
{"learn":[4.577555199],"iteration":263,"passed_time":0.4619226691,"remaining_time":1.287784411},
{"learn":[4.57457145],"iteration":264,"passed_time":0.4631361254,"remaining_time":1.284547367},
{"learn":[4.573029224],"iteration":265,"passed_time":0.464365012,"remaining_time":1.281368116},
{"learn":[4.571326203],"iteration":266,"passed_time":0.4656297307,"remaining_time":1.278301845},
{"learn":[4.571019224],"iteration":267,"passed_time":0.466471086,"remaining_time":1.274092668},
{"learn":[4.565766631],"iteration":268,"passed_time":0.4672770148,"remaining_time":1.26981226},
{"learn":[4.563383471],"iteration":269,"passed_time":0.4681911061,"remaining_time":1.265850028},
{"learn":[4.558165805],"iteration":270,"passed_time":0.4690007314,"remaining_time":1.261629274},
{"learn":[4.55629209],"iteration":271,"passed_time":0.469897127,"remaining_time":1.25766584},
{"learn":[4.549383848],"iteration":272,"passed_time":0.47067407,"remaining_time":1.253406773},
{"learn":[4.546227503],"iteration":273,"passed_time":0.4714132047,"remaining_time":1.249072944},
{"learn":[4.540620977],"iteration":274,"passed_time":0.4722406633,"remaining_time":1.244998112},
{"learn":[4.532898237],"iteration":275,"passed_time":0.4730175205,"remaining_time":1.240814075},
{"learn":[4.529757367],"iteration":276,"passed_time":0.473808336,"remaining_time":1.236691072},
{"learn":[4.52579294],"iteration":277,"passed_time":0.4745790087,"remaining_time":1.232539728},
{"learn":[4.521572155],"iteration":278,"passed_time":0.4753598548,"remaining_time":1.228438908},
{"learn":[4.518818099],"iteration":279,"passed_time":0.4762210977,"remaining_time":1.224568537},
{"learn":[4.514012334],"iteration":280,"passed_time":0.4772425997,"remaining_time":1.221129641},
{"learn":[4.508331416],"iteration":281,"passed_time":0.4783533876,"remaining_time":1.217935221},
{"learn":[4.506038537],"iteration":282,"passed_time":0.4797010539,"remaining_time":1.215355674},
{"learn":[4.505805643],"iteration":283,"passed_time":0.4805704703,"remaining_time":1.211579073},
{"learn":[4.501550352],"iteration":284,"passed_time":0.4813254488,"remaining_time":1.207535775},
{"learn":[4.494692643],"iteration":285,"passed_time":0.482119595,"remaining_time":1.203613255},
{"learn":[4.489330245],"iteration":286,"passed_time":0.4828812042,"remaining_time":1.199631703},
{"learn":[4.484826955],"iteration":287,"passed_time":0.4836718655,"remaining_time":1.195744334},
{"learn":[4.478285428],"iteration":288,"passed_time":0.4844353833,"remaining_time":1.191811618},
{"learn":[4.475311671],"iteration":289,"passed_time":0.4852082947,"remaining_time":1.187923756},
{"learn":[4.471581298],"iteration":290,"passed_time":0.4859501032,"remaining_time":1.183981523},
{"learn":[4.469164956],"iteration":291,"passed_time":0.4866770713,"remaining_time":1.180025228},
{"learn":[4.462068024],"iteration":292,"passed_time":0.487504835,"remaining_time":1.176334192},
{"learn":[4.458540976],"iteration":293,"passed_time":0.4883793495,"remaining_time":1.1727749},
{"learn":[4.455757458],"iteration":294,"passed_time":0.4892844502,"remaining_time":1.169306906},
{"learn":[4.453027414],"iteration":295,"passed_time":0.490359899,"remaining_time":1.166261381},
{"learn":[4.450659338],"iteration":296,"passed_time":0.4913474705,"remaining_time":1.163021117},
{"learn":[4.444696901],"iteration":297,"passed_time":0.4923607477,"remaining_time":1.159856527},
{"learn":[4.442052813],"iteration":298,"passed_time":0.4933424317,"remaining_time":1.156632256},
{"learn":[4.440036756],"iteration":299,"passed_time":0.4945554116,"remaining_time":1.153962627},
{"learn":[4.435017051],"iteration":300,"passed_time":0.4953785275,"remaining_time":1.150397311},
{"learn":[4.429962125],"iteration":301,"passed_time":0.4961376995,"remaining_time":1.146702365},
{"learn":[4.427666256],"iteration":302,"passed_time":0.4968978253,"remaining_time":1.143028991},
{"learn":[4.425030004],"iteration":303,"passed_time":0.497659126,"remaining_time":1.139377473},
{"learn":[4.422588771],"iteration":304,"passed_time":0.498402532,"remaining_time":1.13570413},
{"learn":[4.418936667],"iteration":305,"passed_time":0.4991683905,"remaining_time":1.13210086},
{"learn":[4.416887976],"iteration":306,"passed_time":0.4999425958,"remaining_time":1.128534915},
{"learn":[4.413773354],"iteration":307,"passed_time":0.5006993271,"remaining_time":1.124947839},
{"learn":[4.411129391],"iteration":308,"passed_time":0.5015365769,"remaining_time":1.121559141},
{"learn":[4.40850819],"iteration":309,"passed_time":0.5023132636,"remaining_time":1.118052103},
{"learn":[4.404880292],"iteration":310,"passed_time":0.5030882755,"remaining_time":1.114558913},
{"learn":[4.404593827],"iteration":311,"passed_time":0.5039155538,"remaining_time":1.111198401},
{"learn":[4.402139942],"iteration":312,"passed_time":0.5046616362,"remaining_time":1.10767586},
{"learn":[4.400284725],"iteration":313,"passed_time":0.5054899808,"remaining_time":1.104350722},
{"learn":[4.395805521],"iteration":314,"passed_time":0.5064551932,"remaining_time":1.101339071},
{"learn":[4.392838833],"iteration":315,"passed_time":0.5073813027,"remaining_time":1.098255731},
{"learn":[4.389213061],"iteration":316,"passed_time":0.5084560244,"remaining_time":1.095506198},
{"learn":[4.3861981],"iteration":317,"passed_time":0.5096569956,"remaining_time":1.093037959},
{"learn":[4.385054234],"iteration":318,"passed_time":0.5104310597,"remaining_time":1.089666306},
{"learn":[4.379364607],"iteration":319,"passed_time":0.511205539,"remaining_time":1.08631177},
{"learn":[4.378387619],"iteration":320,"passed_time":0.5119471635,"remaining_time":1.082903813},
{"learn":[4.375816727],"iteration":321,"passed_time":0.5127132678,"remaining_time":1.079563961},
{"learn":[4.374600202],"iteration":322,"passed_time":0.5134481456,"remaining_time":1.076174596},
{"learn":[4.37098897],"iteration":323,"passed_time":0.5143758807,"remaining_time":1.073203998},
{"learn":[4.367418484],"iteration":324,"passed_time":0.5151697636,"remaining_time":1.069967971},
{"learn":[4.363584638],"iteration":325,"passed_time":0.5159506143,"remaining_time":1.066719982},
{"learn":[4.360770706],"iteration":326,"passed_time":0.5167811333,"remaining_time":1.063589305},
{"learn":[4.358675808],"iteration":327,"passed_time":0.5175666448,"remaining_time":1.060380443},
{"learn":[4.354228195],"iteration":328,"passed_time":0.5183550151,"remaining_time":1.057192143},
{"learn":[4.353773425],"iteration":329,"passed_time":0.5191278852,"remaining_time":1.053986918},
{"learn":[4.351648009],"iteration":330,"passed_time":0.5198819421,"remaining_time":1.050758366},
{"learn":[4.348209927],"iteration":331,"passed_time":0.5207666969,"remaining_time":1.047807691},
{"learn":[4.345852733],"iteration":332,"passed_time":0.521674666,"remaining_time":1.044915923},
{"learn":[4.34237339],"iteration":333,"passed_time":0.5227071203,"remaining_time":1.042284258},
{"learn":[4.340814362],"iteration":334,"passed_time":0.524042681,"remaining_time":1.040263829},
{"learn":[4.339707068],"iteration":335,"passed_time":0.5248045274,"remaining_time":1.037113709},
{"learn":[4.335430786],"iteration":336,"passed_time":0.5255865911,"remaining_time":1.034017537},
{"learn":[4.33521887],"iteration":337,"passed_time":0.5263190965,"remaining_time":1.030837994},
{"learn":[4.328507238],"iteration":338,"passed_time":0.5270672221,"remaining_time":1.027703345},
{"learn":[4.326140732],"iteration":339,"passed_time":0.5278358978,"remaining_time":1.024622625},
{"learn":[4.323785636],"iteration":340,"passed_time":0.528592227,"remaining_time":1.021531606},
{"learn":[4.320632534],"iteration":341,"passed_time":0.5293474568,"remaining_time":1.018452124},
{"learn":[4.31973724],"iteration":342,"passed_time":0.530160257,"remaining_time":1.015496469},
{"learn":[4.318000924],"iteration":343,"passed_time":0.5310818026,"remaining_time":1.012760647},
{"learn":[4.312713628],"iteration":344,"passed_time":0.5319066839,"remaining_time":1.00985182},
{"learn":[4.308220789],"iteration":345,"passed_time":0.5327361883,"remaining_time":1.006963778},
{"learn":[4.305890947],"iteration":346,"passed_time":0.5335636666,"remaining_time":1.004083788},
{"learn":[4.305137856],"iteration":347,"passed_time":0.5343332266,"remaining_time":1.00110708},
{"learn":[4.304787172],"iteration":348,"passed_time":0.5351512782,"remaining_time":0.9982334731},
{"learn":[4.30350134],"iteration":349,"passed_time":0.53615947,"remaining_time":0.9957247299},
{"learn":[4.30293809],"iteration":350,"passed_time":0.5371369825,"remaining_time":0.993167811},
{"learn":[4.299548459],"iteration":351,"passed_time":0.5382983192,"remaining_time":0.9909582694},
{"learn":[4.294768408],"iteration":352,"passed_time":0.5391768236,"remaining_time":0.9882362745},
{"learn":[4.294581479],"iteration":353,"passed_time":0.53989186,"remaining_time":0.9852263885},
{"learn":[4.292551604],"iteration":354,"passed_time":0.5407086512,"remaining_time":0.9824143099},
{"learn":[4.288628894],"iteration":355,"passed_time":0.5414670549,"remaining_time":0.9795078183},
{"learn":[4.287802767],"iteration":356,"passed_time":0.5422224037,"remaining_time":0.9766078588},
{"learn":[4.284566905],"iteration":357,"passed_time":0.5430173821,"remaining_time":0.9737909479},
{"learn":[4.27890232],"iteration":358,"passed_time":0.5438025956,"remaining_time":0.9709678657},
{"learn":[4.276938023],"iteration":359,"passed_time":0.5446882072,"remaining_time":0.9683345906},
{"learn":[4.273425094],"iteration":360,"passed_time":0.5455716243,"remaining_time":0.9657071133},
{"learn":[4.269726505],"iteration":361,"passed_time":0.5464345989,"remaining_time":0.9630532434},
{"learn":[4.265565857],"iteration":362,"passed_time":0.5472199204,"remaining_time":0.9602729733},
{"learn":[4.262117173],"iteration":363,"passed_time":0.5481342574,"remaining_time":0.9577290872},
{"learn":[4.259185148],"iteration":364,"passed_time":0.5490874758,"remaining_time":0.9552617729},
{"learn":[4.257668507],"iteration":365,"passed_time":0.5502195528,"remaining_time":0.9531125587},
{"learn":[4.253432436],"iteration":366,"passed_time":0.5516936717,"remaining_time":0.9515588398},
{"learn":[4.250216667],"iteration":367,"passed_time":0.5538506111,"remaining_time":0.9511782234},
{"learn":[4.24514828],"iteration":368,"passed_time":0.5551161257,"remaining_time":0.9492636188},
{"learn":[4.244015772],"iteration":369,"passed_time":0.5561492153,"remaining_time":0.9469567719},
{"learn":[4.240329192],"iteration":370,"passed_time":0.5572332933,"remaining_time":0.9447432385},
{"learn":[4.236718014],"iteration":371,"passed_time":0.5583156421,"remaining_time":0.9425328583},
{"learn":[4.233495944],"iteration":372,"passed_time":0.5596294292,"remaining_time":0.940717566},
{"learn":[4.230357491],"iteration":373,"passed_time":0.560690123,"remaining_time":0.9384813289},
{"learn":[4.227381215],"iteration":374,"passed_time":0.5615688903,"remaining_time":0.9359481505},
{"learn":[4.226169067],"iteration":375,"passed_time":0.5625591462,"remaining_time":0.9336087959},
{"learn":[4.225963861],"iteration":376,"passed_time":0.5634268742,"remaining_time":0.9310741183},
{"learn":[4.224346548],"iteration":377,"passed_time":0.5644624331,"remaining_time":0.9288244269},
{"learn":[4.222595381],"iteration":378,"passed_time":0.5654622499,"remaining_time":0.9265225783},
{"learn":[4.219700938],"iteration":379,"passed_time":0.5696519011,"remaining_time":0.9294320492},
{"learn":[4.216356207],"iteration":380,"passed_time":0.5708376014,"remaining_time":0.9274238195},
{"learn":[4.214326494],"iteration":381,"passed_time":0.571788698,"remaining_time":0.9250403544},
{"learn":[4.212901398],"iteration":382,"passed_time":0.5726592321,"remaining_time":0.9225345853},
{"learn":[4.211331091],"iteration":383,"passed_time":0.5736508538,"remaining_time":0.920231578},
{"learn":[4.208624791],"iteration":384,"passed_time":0.5745417142,"remaining_time":0.9177744265},
{"learn":[4.204659106],"iteration":385,"passed_time":0.5758146968,"remaining_time":0.9159332223},
{"learn":[4.202968852],"iteration":386,"passed_time":0.5766887579,"remaining_time":0.9134630714},
{"learn":[4.197261935],"iteration":387,"passed_time":0.5776149383,"remaining_time":0.9110833563},
{"learn":[4.196934403],"iteration":388,"passed_time":0.5784487041,"remaining_time":0.9085659593},
{"learn":[4.192479929],"iteration":389,"passed_time":0.5795580557,"remaining_time":0.906488241},
{"learn":[4.190243116],"iteration":390,"passed_time":0.5809358073,"remaining_time":0.9048335208},
{"learn":[4.185852431],"iteration":391,"passed_time":0.582705249,"remaining_time":0.9037877331},
{"learn":[4.180967944],"iteration":392,"passed_time":0.5841688492,"remaining_time":0.9022658816},
{"learn":[4.178283162],"iteration":393,"passed_time":0.5851680012,"remaining_time":0.9000299714},
{"learn":[4.176341157],"iteration":394,"passed_time":0.5861564938,"remaining_time":0.8977839968},
{"learn":[4.176041504],"iteration":395,"passed_time":0.5870308801,"remaining_time":0.8953703322},
{"learn":[4.175564513],"iteration":396,"passed_time":0.5879511955,"remaining_time":0.8930341836},
{"learn":[4.170830274],"iteration":397,"passed_time":0.5889049948,"remaining_time":0.8907557961},
{"learn":[4.167804808],"iteration":398,"passed_time":0.5899086719,"remaining_time":0.8885591775},
{"learn":[4.165860548],"iteration":399,"passed_time":0.59085745,"remaining_time":0.886286175},
{"learn":[4.160950571],"iteration":400,"passed_time":0.591798734,"remaining_time":0.8840085827},
{"learn":[4.158544115],"iteration":401,"passed_time":0.5927346401,"remaining_time":0.8817296387},
{"learn":[4.154448767],"iteration":402,"passed_time":0.593614638,"remaining_time":0.8793745382},
{"learn":[4.15197457],"iteration":403,"passed_time":0.5947584117,"remaining_time":0.8774158746},
{"learn":[4.149562679],"iteration":404,"passed_time":0.5960255927,"remaining_time":0.8756425374},
{"learn":[4.149327961],"iteration":405,"passed_time":0.59784246,"remaining_time":0.8746759144},
{"learn":[4.147444889],"iteration":406,"passed_time":0.5992541531,"remaining_time":0.8731147735},
{"learn":[4.147254809],"iteration":407,"passed_time":0.6001759817,"remaining_time":0.8708435813},
{"learn":[4.144589165],"iteration":408,"passed_time":0.6011222266,"remaining_time":0.8686142687},
{"learn":[4.141691034],"iteration":409,"passed_time":0.602151696,"remaining_time":0.8665109771},
{"learn":[4.138893468],"iteration":410,"passed_time":0.6031339729,"remaining_time":0.8643452799},
{"learn":[4.136964597],"iteration":411,"passed_time":0.6040619769,"remaining_time":0.8621078699},
{"learn":[4.133773523],"iteration":412,"passed_time":0.6050275662,"remaining_time":0.8599302212},
{"learn":[4.131363444],"iteration":413,"passed_time":0.6060062692,"remaining_time":0.8577769897},
{"learn":[4.130228592],"iteration":414,"passed_time":0.6068165151,"remaining_time":0.8553919551},
{"learn":[4.12884186],"iteration":415,"passed_time":0.607709868,"remaining_time":0.8531311608},
{"learn":[4.12413494],"iteration":416,"passed_time":0.6085612626,"remaining_time":0.850818264},
{"learn":[4.119422508],"iteration":417,"passed_time":0.6095908104,"remaining_time":0.8487604106},
{"learn":[4.117038244],"iteration":418,"passed_time":0.6110773561,"remaining_time":0.8473411548},
{"learn":[4.116067631],"iteration":419,"passed_time":0.6129342736,"remaining_time":0.8464330445},
{"learn":[4.110343455],"iteration":420,"passed_time":0.6144316134,"remaining_time":0.8450259005},
{"learn":[4.105604544],"iteration":421,"passed_time":0.6153982961,"remaining_time":0.8428915051},
{"learn":[4.103390131],"iteration":422,"passed_time":0.6162791313,"remaining_time":0.8406455289},
{"learn":[4.096724402],"iteration":423,"passed_time":0.6171069844,"remaining_time":0.8383340166},
{"learn":[4.093431279],"iteration":424,"passed_time":0.6179073187,"remaining_time":0.8359922547},
{"learn":[4.091412744],"iteration":425,"passed_time":0.6187230134,"remaining_time":0.8336784265},
{"learn":[4.091192901],"iteration":426,"passed_time":0.6194968102,"remaining_time":0.8313153917},
{"learn":[4.088994581],"iteration":427,"passed_time":0.6202672698,"remaining_time":0.8289553232},
{"learn":[4.087845355],"iteration":428,"passed_time":0.6210280604,"remaining_time":0.826589796},
{"learn":[4.083650279],"iteration":429,"passed_time":0.6217882716,"remaining_time":0.8242309647},
{"learn":[4.079840652],"iteration":430,"passed_time":0.6225508994,"remaining_time":0.8218827419},
{"learn":[4.075707828],"iteration":431,"passed_time":0.6233528227,"remaining_time":0.8195935261},
{"learn":[4.071345409],"iteration":432,"passed_time":0.6243753905,"remaining_time":0.8176001072},
{"learn":[4.067460475],"iteration":433,"passed_time":0.6255515549,"remaining_time":0.8158114749},
{"learn":[4.064914749],"iteration":434,"passed_time":0.6268097755,"remaining_time":0.8141322372},
{"learn":[4.063823175],"iteration":435,"passed_time":0.6275572751,"remaining_time":0.8117942732},
{"learn":[4.058898471],"iteration":436,"passed_time":0.628443258,"remaining_time":0.8096420006},
{"learn":[4.054120355],"iteration":437,"passed_time":0.6293073281,"remaining_time":0.8074673936},
{"learn":[4.052715901],"iteration":438,"passed_time":0.6301101227,"remaining_time":0.8052204529},
{"learn":[4.052114167],"iteration":439,"passed_time":0.6308444789,"remaining_time":0.8028929731},
{"learn":[4.051377267],"iteration":440,"passed_time":0.6315613961,"remaining_time":0.8005506132},
{"learn":[4.049275336],"iteration":441,"passed_time":0.6324878443,"remaining_time":0.7984801293},
{"learn":[4.047099198],"iteration":442,"passed_time":0.633269105,"remaining_time":0.7962322607},
{"learn":[4.044348685],"iteration":443,"passed_time":0.6340555818,"remaining_time":0.7939975304},
{"learn":[4.042822379],"iteration":444,"passed_time":0.6348244972,"remaining_time":0.7917474066},
{"learn":[4.041258611],"iteration":445,"passed_time":0.6355785264,"remaining_time":0.7894854341},
{"learn":[4.040044254],"iteration":446,"passed_time":0.6363641082,"remaining_time":0.7872692435},
{"learn":[4.036860137],"iteration":447,"passed_time":0.6371175169,"remaining_time":0.7850197976},
{"learn":[4.036372284],"iteration":448,"passed_time":0.6378617319,"remaining_time":0.7827657334},
{"learn":[4.03368231],"iteration":449,"passed_time":0.6387212352,"remaining_time":0.7806592874},
{"learn":[4.032439519],"iteration":450,"passed_time":0.6397019106,"remaining_time":0.7787058734},
{"learn":[4.032008634],"iteration":451,"passed_time":0.6406764382,"remaining_time":0.77674931},
{"learn":[4.030034932],"iteration":452,"passed_time":0.6414797383,"remaining_time":0.7745903242},
{"learn":[4.028173412],"iteration":453,"passed_time":0.6422288861,"remaining_time":0.7723721846},
{"learn":[4.023806097],"iteration":454,"passed_time":0.6430291188,"remaining_time":0.7702216918},
{"learn":[4.020239186],"iteration":455,"passed_time":0.6437918899,"remaining_time":0.76803243},
{"learn":[4.017384838],"iteration":456,"passed_time":0.6445784406,"remaining_time":0.7658776657},
{"learn":[4.016468229],"iteration":457,"passed_time":0.6453199491,"remaining_time":0.7636755729},
{"learn":[4.014530169],"iteration":458,"passed_time":0.6461042586,"remaining_time":0.7615302917},
{"learn":[4.012884822],"iteration":459,"passed_time":0.6468557611,"remaining_time":0.7593524152},
{"learn":[4.008924707],"iteration":460,"passed_time":0.6476175573,"remaining_time":0.7571927622},
{"learn":[4.008286778],"iteration":461,"passed_time":0.6483619854,"remaining_time":0.7550189354},
{"learn":[4.006444202],"iteration":462,"passed_time":0.6491213926,"remaining_time":0.7528686562},
{"learn":[4.003284363],"iteration":463,"passed_time":0.6498807832,"remaining_time":0.750724353},
{"learn":[3.999811484],"iteration":464,"passed_time":0.6506413175,"remaining_time":0.7485873223},
{"learn":[3.997483319],"iteration":465,"passed_time":0.6515068671,"remaining_time":0.7465765387},
{"learn":[3.99708333],"iteration":466,"passed_time":0.6524221041,"remaining_time":0.7446273693},
{"learn":[3.995860263],"iteration":467,"passed_time":0.6533910829,"remaining_time":0.7427437096},
{"learn":[3.994131111],"iteration":468,"passed_time":0.6543651597,"remaining_time":0.7408697224},
{"learn":[3.993125499],"iteration":469,"passed_time":0.6555586751,"remaining_time":0.7392470166},
{"learn":[3.992954084],"iteration":470,"passed_time":0.656381889,"remaining_time":0.737210232},
{"learn":[3.990635743],"iteration":471,"passed_time":0.6572397515,"remaining_time":0.7352173492},
{"learn":[3.986678254],"iteration":472,"passed_time":0.6580691791,"remaining_time":0.7331975843},
{"learn":[3.986393291],"iteration":473,"passed_time":0.6589873634,"remaining_time":0.7312813357},
{"learn":[3.986152671],"iteration":474,"passed_time":0.6600399586,"remaining_time":0.729517849},
{"learn":[3.985596662],"iteration":475,"passed_time":0.6609710591,"remaining_time":0.7276236029},
{"learn":[3.983853457],"iteration":476,"passed_time":0.6620070356,"remaining_time":0.725848385},
{"learn":[3.983263928],"iteration":477,"passed_time":0.663040087,"remaining_time":0.7240730657},
{"learn":[3.980067202],"iteration":478,"passed_time":0.6639030415,"remaining_time":0.7221158343},
{"learn":[3.978115407],"iteration":479,"passed_time":0.664699925,"remaining_time":0.7200915854},
{"learn":[3.972661644],"iteration":480,"passed_time":0.6655423894,"remaining_time":0.7181216218},
{"learn":[3.969938254],"iteration":481,"passed_time":0.6666070737,"remaining_time":0.7163951539},
{"learn":[3.968211434],"iteration":482,"passed_time":0.6675053502,"remaining_time":0.7144933045},
{"learn":[3.966113368],"iteration":483,"passed_time":0.668528114,"remaining_time":0.7127283199},
{"learn":[3.962246044],"iteration":484,"passed_time":0.669646814,"remaining_time":0.7110682664},
{"learn":[3.961319703],"iteration":485,"passed_time":0.6706930675,"remaining_time":0.7093338204},
{"learn":[3.96078191],"iteration":486,"passed_time":0.6714798544,"remaining_time":0.7073288815},
{"learn":[3.958913633],"iteration":487,"passed_time":0.672323064,"remaining_time":0.7053881327},
{"learn":[3.957428286],"iteration":488,"passed_time":0.6731422201,"remaining_time":0.7034267371},
{"learn":[3.952641965],"iteration":489,"passed_time":0.6739672431,"remaining_time":0.7014761101},
{"learn":[3.951486786],"iteration":490,"passed_time":0.6748198618,"remaining_time":0.6995586755},
{"learn":[3.94938344],"iteration":491,"passed_time":0.6756119633,"remaining_time":0.6975830841},
{"learn":[3.947297924],"iteration":492,"passed_time":0.6765127941,"remaining_time":0.6957241108},
{"learn":[3.946284886],"iteration":493,"passed_time":0.6773715371,"remaining_time":0.6938259064},
{"learn":[3.943288204],"iteration":494,"passed_time":0.6782089642,"remaining_time":0.6919101554},
{"learn":[3.943076488],"iteration":495,"passed_time":0.6789849474,"remaining_time":0.6899363176},
{"learn":[3.942347078],"iteration":496,"passed_time":0.6797668654,"remaining_time":0.6879733065},
{"learn":[3.940251541],"iteration":497,"passed_time":0.6805846974,"remaining_time":0.6860512411},
{"learn":[3.939011019],"iteration":498,"passed_time":0.6814349141,"remaining_time":0.6841661161},
{"learn":[3.938760512],"iteration":499,"passed_time":0.6821624199,"remaining_time":0.6821624199},
{"learn":[3.934522727],"iteration":500,"passed_time":0.6830117411,"remaining_time":0.6802851474},
{"learn":[3.930091193],"iteration":501,"passed_time":0.6853876024,"remaining_time":0.6799263466},
{"learn":[3.927671752],"iteration":502,"passed_time":0.6866107493,"remaining_time":0.6784205614},
{"learn":[3.927280041],"iteration":503,"passed_time":0.6875835869,"remaining_time":0.6766695617},
{"learn":[3.925987561],"iteration":504,"passed_time":0.6884349117,"remaining_time":0.6748025372},
{"learn":[3.921645957],"iteration":505,"passed_time":0.6893604895,"remaining_time":0.6730120194},
{"learn":[3.920333743],"iteration":506,"passed_time":0.6901569122,"remaining_time":0.6710993249},
{"learn":[3.918659461],"iteration":507,"passed_time":0.6910206446,"remaining_time":0.6692562149},
{"learn":[3.916124385],"iteration":508,"passed_time":0.6918640271,"remaining_time":0.6673973228},
{"learn":[3.913849268],"iteration":509,"passed_time":0.6927709318,"remaining_time":0.6656034443},
{"learn":[3.912826119],"iteration":510,"passed_time":0.6936503092,"remaining_time":0.6637866951},
{"learn":[3.910034145],"iteration":511,"passed_time":0.6944782015,"remaining_time":0.6619245358},
{"learn":[3.90792379],"iteration":512,"passed_time":0.6954534362,"remaining_time":0.6602062834},
{"learn":[3.907823851],"iteration":513,"passed_time":0.6962552237,"remaining_time":0.6583269236},
{"learn":[3.904527401],"iteration":514,"passed_time":0.6971398533,"remaining_time":0.6565297648},
{"learn":[3.903378283],"iteration":515,"passed_time":0.6983591303,"remaining_time":0.655050037},
{"learn":[3.902170135],"iteration":516,"passed_time":0.7017226545,"remaining_time":0.6555745496},
{"learn":[3.899435429],"iteration":517,"passed_time":0.70338029,"remaining_time":0.6544967177},
{"learn":[3.897497505],"iteration":518,"passed_time":0.7045262009,"remaining_time":0.6529423942},
{"learn":[3.896426119],"iteration":519,"passed_time":0.7055472656,"remaining_time":0.6512743991},
{"learn":[3.896044669],"iteration":520,"passed_time":0.7064288963,"remaining_time":0.6494806935},
{"learn":[3.892795942],"iteration":521,"passed_time":0.7074373107,"remaining_time":0.6478065795},
{"learn":[3.892413888],"iteration":522,"passed_time":0.7081518028,"remaining_time":0.6458669406},
{"learn":[3.891738985],"iteration":523,"passed_time":0.7089416224,"remaining_time":0.644000405},
{"learn":[3.88822057],"iteration":524,"passed_time":0.709758594,"remaining_time":0.6421625374},
{"learn":[3.883837053],"iteration":525,"passed_time":0.7105303626,"remaining_time":0.6402878173},
{"learn":[3.881769742],"iteration":526,"passed_time":0.7112962568,"remaining_time":0.6384120104},
{"learn":[3.880356898],"iteration":527,"passed_time":0.7120599088,"remaining_time":0.6365384033},
{"learn":[3.879250273],"iteration":528,"passed_time":0.7131309359,"remaining_time":0.6349426669},
{"learn":[3.877174493],"iteration":529,"passed_time":0.7141376216,"remaining_time":0.6332918531},
{"learn":[3.875854201],"iteration":530,"passed_time":0.7153732556,"remaining_time":0.6318456815},
{"learn":[3.873189396],"iteration":531,"passed_time":0.716894372,"remaining_time":0.63065144},
{"learn":[3.871583368],"iteration":532,"passed_time":0.7181674244,"remaining_time":0.6292386251},
{"learn":[3.869622679],"iteration":533,"passed_time":0.7190121998,"remaining_time":0.6274525939},
{"learn":[3.866860164],"iteration":534,"passed_time":0.7198305846,"remaining_time":0.6256471436},
{"learn":[3.864498444],"iteration":535,"passed_time":0.7206474763,"remaining_time":0.6238440839},
{"learn":[3.861416322],"iteration":536,"passed_time":0.7215312848,"remaining_time":0.6221023927},
{"learn":[3.860265769],"iteration":537,"passed_time":0.7223012213,"remaining_time":0.6202661045},
{"learn":[3.859328725],"iteration":538,"passed_time":0.7230454725,"remaining_time":0.6184118049},
{"learn":[3.858521278],"iteration":539,"passed_time":0.7238075863,"remaining_time":0.6165768327},
{"learn":[3.85599111],"iteration":540,"passed_time":0.7245788393,"remaining_time":0.6147535808},
{"learn":[3.852379816],"iteration":541,"passed_time":0.7253365882,"remaining_time":0.6129227996},
{"learn":[3.851327537],"iteration":542,"passed_time":0.7260688363,"remaining_time":0.6110745086},
{"learn":[3.847854898],"iteration":543,"passed_time":0.7268485909,"remaining_time":0.6092701424},
{"learn":[3.847083414],"iteration":544,"passed_time":0.7278940429,"remaining_time":0.6076913569},
{"learn":[3.845397429],"iteration":545,"passed_time":0.7289105574,"remaining_time":0.6060904635},
{"learn":[3.841933528],"iteration":546,"passed_time":0.7299517591,"remaining_time":0.6045121515},
{"learn":[3.840996474],"iteration":547,"passed_time":0.7313560617,"remaining_time":0.6032352917},
{"learn":[3.838355966],"iteration":548,"passed_time":0.7322733756,"remaining_time":0.6015579096},
{"learn":[3.83342799],"iteration":549,"passed_time":0.7330152655,"remaining_time":0.5997397627},
{"learn":[3.828161535],"iteration":550,"passed_time":0.7338308356,"remaining_time":0.5979855629},
{"learn":[3.823502399],"iteration":551,"passed_time":0.7346523706,"remaining_time":0.5962396051},
{"learn":[3.820068862],"iteration":552,"passed_time":0.7354370368,"remaining_time":0.5944671889},
{"learn":[3.817951642],"iteration":553,"passed_time":0.7361735965,"remaining_time":0.5926596102},
{"learn":[3.815785958],"iteration":554,"passed_time":0.7369083085,"remaining_time":0.5908544095},
{"learn":[3.81503012],"iteration":555,"passed_time":0.737651707,"remaining_time":0.5890599962},
{"learn":[3.813529315],"iteration":556,"passed_time":0.738383844,"remaining_time":0.5872604002},
{"learn":[3.808881326],"iteration":557,"passed_time":0.7391301103,"remaining_time":0.5854758222},
{"learn":[3.808740434],"iteration":558,"passed_time":0.7398567554,"remaining_time":0.5836794796},
{"learn":[3.80714352],"iteration":559,"passed_time":0.7408311191,"remaining_time":0.5820815936},
{"learn":[3.80573346],"iteration":560,"passed_time":0.741695625,"remaining_time":0.5803999632},
{"learn":[3.803370052],"iteration":561,"passed_time":0.7428170516,"remaining_time":0.5789214744},
{"learn":[3.803215211],"iteration":562,"passed_time":0.7440823864,"remaining_time":0.5775559553},
{"learn":[3.801309667],"iteration":563,"passed_time":0.7455064842,"remaining_time":0.5763135232},
{"learn":[3.800003847],"iteration":564,"passed_time":0.7462980168,"remaining_time":0.5745834289},
{"learn":[3.798026138],"iteration":565,"passed_time":0.7470549587,"remaining_time":0.5728301273},
{"learn":[3.794745847],"iteration":566,"passed_time":0.7478034391,"remaining_time":0.5710738785},
{"learn":[3.794312041],"iteration":567,"passed_time":0.7485739444,"remaining_time":0.5693379295},
{"learn":[3.792205926],"iteration":568,"passed_time":0.7493620298,"remaining_time":0.5676186904},
{"learn":[3.788991061],"iteration":569,"passed_time":0.7501226445,"remaining_time":0.565881995},
{"learn":[3.787391572],"iteration":570,"passed_time":0.7508929232,"remaining_time":0.5641559791},
{"learn":[3.7826445],"iteration":571,"passed_time":0.7516790618,"remaining_time":0.5624451721},
{"learn":[3.781700331],"iteration":572,"passed_time":0.7524458022,"remaining_time":0.5607231371},
{"learn":[3.780045374],"iteration":573,"passed_time":0.7531885042,"remaining_time":0.5589865902},
{"learn":[3.775462644],"iteration":574,"passed_time":0.7540154026,"remaining_time":0.5573157323},
{"learn":[3.773711943],"iteration":575,"passed_time":0.7547590151,"remaining_time":0.5555864972},
{"learn":[3.772415806],"iteration":576,"passed_time":0.7555520106,"remaining_time":0.5538968813},
{"learn":[3.770170875],"iteration":577,"passed_time":0.7563087072,"remaining_time":0.5521838658},
{"learn":[3.765166479],"iteration":578,"passed_time":0.7571928911,"remaining_time":0.5505668518},
{"learn":[3.763976102],"iteration":579,"passed_time":0.7581901959,"remaining_time":0.5490342798},
{"learn":[3.760761708],"iteration":580,"passed_time":0.7592330348,"remaining_time":0.5475363882},
{"learn":[3.758155662],"iteration":581,"passed_time":0.7601054406,"remaining_time":0.5459176532},
{"learn":[3.756844548],"iteration":582,"passed_time":0.7609035372,"remaining_time":0.5442483276},
{"learn":[3.753098923],"iteration":583,"passed_time":0.7616679073,"remaining_time":0.5425579613},
{"learn":[3.751618946],"iteration":584,"passed_time":0.7624023393,"remaining_time":0.5408495227},
{"learn":[3.751398464],"iteration":585,"passed_time":0.7631300899,"remaining_time":0.5391396881},
{"learn":[3.749920103],"iteration":586,"passed_time":0.7638425915,"remaining_time":0.5374224707},
{"learn":[3.748237465],"iteration":587,"passed_time":0.7645967725,"remaining_time":0.5357378746},
{"learn":[3.746021536],"iteration":588,"passed_time":0.7654100315,"remaining_time":0.5340976621},
{"learn":[3.74417648],"iteration":589,"passed_time":0.7661609522,"remaining_time":0.5324169329},
{"learn":[3.738788389],"iteration":590,"passed_time":0.7669453089,"remaining_time":0.5307624896},
{"learn":[3.736021611],"iteration":591,"passed_time":0.7678584052,"remaining_time":0.5291997117},
{"learn":[3.734546151],"iteration":592,"passed_time":0.7686956504,"remaining_time":0.5275870653},
{"learn":[3.733527479],"iteration":593,"passed_time":0.7694409092,"remaining_time":0.5259141568},
{"learn":[3.733026392],"iteration":594,"passed_time":0.7701868122,"remaining_time":0.524244805},
{"learn":[3.730314752],"iteration":595,"passed_time":0.7709717775,"remaining_time":0.5226050304},
{"learn":[3.727342596],"iteration":596,"passed_time":0.7718111765,"remaining_time":0.5210048645},
{"learn":[3.725459604],"iteration":597,"passed_time":0.7728391871,"remaining_time":0.5195340354},
{"learn":[3.723158842],"iteration":598,"passed_time":0.7738468537,"remaining_time":0.5180510657},
{"learn":[3.722362756],"iteration":599,"passed_time":0.7746642289,"remaining_time":0.5164428192},
{"learn":[3.721443615],"iteration":600,"passed_time":0.7754093032,"remaining_time":0.5147892046},
{"learn":[3.720743486],"iteration":601,"passed_time":0.7761711376,"remaining_time":0.513149689},
{"learn":[3.720215334],"iteration":602,"passed_time":0.7768910981,"remaining_time":0.5114855157},
{"learn":[3.719436563],"iteration":603,"passed_time":0.7776420595,"remaining_time":0.509844794},
{"learn":[3.715046574],"iteration":604,"passed_time":0.7784187583,"remaining_time":0.5082238174},
{"learn":[3.71443396],"iteration":605,"passed_time":0.7791595934,"remaining_time":0.5065823099},
{"learn":[3.712938941],"iteration":606,"passed_time":0.7799025844,"remaining_time":0.5049451658},
{"learn":[3.712814764],"iteration":607,"passed_time":0.7806352219,"remaining_time":0.5033042878},
{"learn":[3.71235348],"iteration":608,"passed_time":0.781471651,"remaining_time":0.5017330305},
{"learn":[3.711223749],"iteration":609,"passed_time":0.7822165008,"remaining_time":0.5001056317},
{"learn":[3.710755648],"iteration":610,"passed_time":0.7829770562,"remaining_time":0.4984911209},
{"learn":[3.708668039],"iteration":611,"passed_time":0.7837474083,"remaining_time":0.4968856118},
{"learn":[3.705623591],"iteration":612,"passed_time":0.7845185839,"remaining_time":0.4952833474},
{"learn":[3.704045802],"iteration":613,"passed_time":0.7853198855,"remaining_time":0.4937027293},
{"learn":[3.699915209],"iteration":614,"passed_time":0.7861177821,"remaining_time":0.492122514},
{"learn":[3.696182221],"iteration":615,"passed_time":0.7870567379,"remaining_time":0.4906327717},
{"learn":[3.694263278],"iteration":616,"passed_time":0.7880189036,"remaining_time":0.4891592222},
{"learn":[3.693810229],"iteration":617,"passed_time":0.7888838792,"remaining_time":0.4876272522},
{"learn":[3.690900932],"iteration":618,"passed_time":0.7896193093,"remaining_time":0.4860177009},
{"learn":[3.688020895],"iteration":619,"passed_time":0.7904095585,"remaining_time":0.4844445681},
{"learn":[3.685491894],"iteration":620,"passed_time":0.7911766723,"remaining_time":0.4828598371},
{"learn":[3.684328128],"iteration":621,"passed_time":0.7919192266,"remaining_time":0.4812628097},
{"learn":[3.680640153],"iteration":622,"passed_time":0.7926961123,"remaining_time":0.4796893007},
{"learn":[3.678932783],"iteration":623,"passed_time":0.7934504114,"remaining_time":0.4781047351},
{"learn":[3.674167041],"iteration":624,"passed_time":0.7943754385,"remaining_time":0.4766252631},
{"learn":[3.672200976],"iteration":625,"passed_time":0.7952651325,"remaining_time":0.475126453},
{"learn":[3.670606604],"iteration":626,"passed_time":0.7961056667,"remaining_time":0.4736003408},
{"learn":[3.665506042],"iteration":627,"passed_time":0.7969237449,"remaining_time":0.47206311},
{"learn":[3.664214007],"iteration":628,"passed_time":0.7977868341,"remaining_time":0.4705547145},
{"learn":[3.66261643],"iteration":629,"passed_time":0.7988151075,"remaining_time":0.4691453806},
{"learn":[3.662118449],"iteration":630,"passed_time":0.7995751368,"remaining_time":0.467580389},
{"learn":[3.660871366],"iteration":631,"passed_time":0.800323278,"remaining_time":0.4660110227},
{"learn":[3.656695243],"iteration":632,"passed_time":0.8011488015,"remaining_time":0.4644891156},
{"learn":[3.654497801],"iteration":633,"passed_time":0.8023302565,"remaining_time":0.4631748799},
{"learn":[3.654189134],"iteration":634,"passed_time":0.8030995648,"remaining_time":0.4616241593},
{"learn":[3.653957699],"iteration":635,"passed_time":0.8039014428,"remaining_time":0.4600945364},
{"learn":[3.651920725],"iteration":636,"passed_time":0.8047630224,"remaining_time":0.45860122},
{"learn":[3.65106705],"iteration":637,"passed_time":0.805620706,"remaining_time":0.4571076733},
{"learn":[3.650612844],"iteration":638,"passed_time":0.806501105,"remaining_time":0.4556289498},
{"learn":[3.649884732],"iteration":639,"passed_time":0.8072664514,"remaining_time":0.4540873789},
{"learn":[3.646276182],"iteration":640,"passed_time":0.8080473729,"remaining_time":0.452556953},
{"learn":[3.645808194],"iteration":641,"passed_time":0.8088674999,"remaining_time":0.4510507242},
{"learn":[3.645042989],"iteration":642,"passed_time":0.8096164763,"remaining_time":0.449507126},
{"learn":[3.639864499],"iteration":643,"passed_time":0.8104178121,"remaining_time":0.4479949396},
{"learn":[3.637318478],"iteration":644,"passed_time":0.8111828761,"remaining_time":0.4464649938},
{"learn":[3.636344905],"iteration":645,"passed_time":0.8119396245,"remaining_time":0.4449328592},
{"learn":[3.634754643],"iteration":646,"passed_time":0.8126829134,"remaining_time":0.4433957781},
{"learn":[3.630724975],"iteration":647,"passed_time":0.8134582996,"remaining_time":0.4418785825},
{"learn":[3.629408252],"iteration":648,"passed_time":0.8142144796,"remaining_time":0.4403532856},
{"learn":[3.62790646],"iteration":649,"passed_time":0.8149761733,"remaining_time":0.4388333241},
{"learn":[3.627388973],"iteration":650,"passed_time":0.8157245371,"remaining_time":0.437308546},
{"learn":[3.625163557],"iteration":651,"passed_time":0.8166427656,"remaining_time":0.4358768136},
{"learn":[3.623701985],"iteration":652,"passed_time":0.8176323708,"remaining_time":0.4344845829},
{"learn":[3.622342639],"iteration":653,"passed_time":0.8186113241,"remaining_time":0.4330879482},
{"learn":[3.621130639],"iteration":654,"passed_time":0.819356916,"remaining_time":0.4315696733},
{"learn":[3.619125665],"iteration":655,"passed_time":0.8201481879,"remaining_time":0.4300777083},
{"learn":[3.618878783],"iteration":656,"passed_time":0.8208768093,"remaining_time":0.4285551683},
{"learn":[3.616207429],"iteration":657,"passed_time":0.8216715732,"remaining_time":0.4270694195},
{"learn":[3.61206486],"iteration":658,"passed_time":0.8225505686,"remaining_time":0.4256293534},
{"learn":[3.611955873],"iteration":659,"passed_time":0.8234282836,"remaining_time":0.4241903279},
{"learn":[3.610713743],"iteration":660,"passed_time":0.8242351033,"remaining_time":0.4227166415},
{"learn":[3.610044025],"iteration":661,"passed_time":0.8249974523,"remaining_time":0.4212222641},
{"learn":[3.607342669],"iteration":662,"passed_time":0.8257557981,"remaining_time":0.4197280603},
{"learn":[3.602510618],"iteration":663,"passed_time":0.8265228958,"remaining_time":0.4182405015},
{"learn":[3.600492392],"iteration":664,"passed_time":0.8273097169,"remaining_time":0.4167650454},
{"learn":[3.597171065],"iteration":665,"passed_time":0.8281082481,"remaining_time":0.4152975298},
{"learn":[3.594358798],"iteration":666,"passed_time":0.8288712021,"remaining_time":0.4138142583},
{"learn":[3.593945251],"iteration":667,"passed_time":0.8296070452,"remaining_time":0.4123196692},
{"learn":[3.593607748],"iteration":668,"passed_time":0.8303672182,"remaining_time":0.410839386},
{"learn":[3.592238714],"iteration":669,"passed_time":0.8312914769,"remaining_time":0.4094420707},
{"learn":[3.590144654],"iteration":670,"passed_time":0.8323144814,"remaining_time":0.4080945818},
{"learn":[3.587151536],"iteration":671,"passed_time":0.8333162912,"remaining_time":0.4067377136},
{"learn":[3.586070865],"iteration":672,"passed_time":0.8340733034,"remaining_time":0.4052629572},
{"learn":[3.585102746],"iteration":673,"passed_time":0.8348231221,"remaining_time":0.4037868513},
{"learn":[3.584362847],"iteration":674,"passed_time":0.8356466455,"remaining_time":0.4023483849},
{"learn":[3.581407561],"iteration":675,"passed_time":0.8365551719,"remaining_time":0.4009524788},
{"learn":[3.57919422],"iteration":676,"passed_time":0.8373766612,"remaining_time":0.3995164868},
{"learn":[3.577632204],"iteration":677,"passed_time":0.8382416539,"remaining_time":0.3981029684},
{"learn":[3.573911195],"iteration":678,"passed_time":0.8390044637,"remaining_time":0.3966427582},
{"learn":[3.573408216],"iteration":679,"passed_time":0.8397384103,"remaining_time":0.3951710166},
{"learn":[3.571076482],"iteration":680,"passed_time":0.840694399,"remaining_time":0.3938054527},
{"learn":[3.568177107],"iteration":681,"passed_time":0.841478917,"remaining_time":0.3923611372},
{"learn":[3.564824621],"iteration":682,"passed_time":0.842214045,"remaining_time":0.3908958306},
{"learn":[3.562475026],"iteration":683,"passed_time":0.8429663401,"remaining_time":0.3894405899},
{"learn":[3.561226889],"iteration":684,"passed_time":0.8437332091,"remaining_time":0.3879941035},
{"learn":[3.559383467],"iteration":685,"passed_time":0.8444708206,"remaining_time":0.3865362065},
{"learn":[3.555209766],"iteration":686,"passed_time":0.8452632915,"remaining_time":0.3851054006},
{"learn":[3.55345383],"iteration":687,"passed_time":0.8462340693,"remaining_time":0.3837573105},
{"learn":[3.552300968],"iteration":688,"passed_time":0.8474371737,"remaining_time":0.3825151829},
{"learn":[3.551253986],"iteration":689,"passed_time":0.8486350645,"remaining_time":0.3812708261},
{"learn":[3.549807725],"iteration":690,"passed_time":0.8494556272,"remaining_time":0.3798578709},
{"learn":[3.547992926],"iteration":691,"passed_time":0.8502130921,"remaining_time":0.3784185439},
{"learn":[3.545438607],"iteration":692,"passed_time":0.850959272,"remaining_time":0.3769761854},
{"learn":[3.543313763],"iteration":693,"passed_time":0.8517268245,"remaining_time":0.3755452569},
{"learn":[3.542962896],"iteration":694,"passed_time":0.8524873584,"remaining_time":0.3741131573},
{"learn":[3.539800465],"iteration":695,"passed_time":0.853277293,"remaining_time":0.3726958291},
{"learn":[3.53953187],"iteration":696,"passed_time":0.8540451445,"remaining_time":0.3712707013},
{"learn":[3.536332425],"iteration":697,"passed_time":0.8548416978,"remaining_time":0.369859875},
{"learn":[3.534993327],"iteration":698,"passed_time":0.8556211942,"remaining_time":0.3684434613},
{"learn":[3.531637011],"iteration":699,"passed_time":0.8563820526,"remaining_time":0.3670208797},
{"learn":[3.531040284],"iteration":700,"passed_time":0.8571572937,"remaining_time":0.3656063207},
{"learn":[3.529973872],"iteration":701,"passed_time":0.8579454946,"remaining_time":0.3641990846},
{"learn":[3.527325183],"iteration":702,"passed_time":0.8587275232,"remaining_time":0.362791002},
{"learn":[3.527200815],"iteration":703,"passed_time":0.8594418917,"remaining_time":0.3613562499},
{"learn":[3.523459911],"iteration":704,"passed_time":0.8602403264,"remaining_time":0.3599587181},
{"learn":[3.522729934],"iteration":705,"passed_time":0.8612702652,"remaining_time":0.3586592889},
{"learn":[3.522260582],"iteration":706,"passed_time":0.8623155262,"remaining_time":0.357366972},
{"learn":[3.518641591],"iteration":707,"passed_time":0.8633700572,"remaining_time":0.3560791761},
{"learn":[3.516856405],"iteration":708,"passed_time":0.8642579582,"remaining_time":0.3547236472},
{"learn":[3.515083413],"iteration":709,"passed_time":0.8652048247,"remaining_time":0.3533935199},
{"learn":[3.514671214],"iteration":710,"passed_time":0.8659469161,"remaining_time":0.3519812359},
{"learn":[3.512617621],"iteration":711,"passed_time":0.866699978,"remaining_time":0.350575272},
{"learn":[3.510747971],"iteration":712,"passed_time":0.8674464172,"remaining_time":0.3491684737},
{"learn":[3.508149266],"iteration":713,"passed_time":0.8681895901,"remaining_time":0.3477622167},
{"learn":[3.504557165],"iteration":714,"passed_time":0.8689558018,"remaining_time":0.3463669979},
{"learn":[3.501367208],"iteration":715,"passed_time":0.8697571813,"remaining_time":0.3449874853},
{"learn":[3.497593362],"iteration":716,"passed_time":0.8705279007,"remaining_time":0.3435974838},
{"learn":[3.496291169],"iteration":717,"passed_time":0.8712644855,"remaining_time":0.3421958007},
{"learn":[3.49330374],"iteration":718,"passed_time":0.8720191454,"remaining_time":0.3408030318},
{"learn":[3.490044385],"iteration":719,"passed_time":0.8727814371,"remaining_time":0.3394150033},
{"learn":[3.488891789],"iteration":720,"passed_time":0.8735462283,"remaining_time":0.3380296778},
{"learn":[3.486869081],"iteration":721,"passed_time":0.8743281332,"remaining_time":0.3366526607},
{"learn":[3.486303638],"iteration":722,"passed_time":0.8750581943,"remaining_time":0.3352574271},
{"learn":[3.486035862],"iteration":723,"passed_time":0.8760955166,"remaining_time":0.3339811638},
{"learn":[3.482668951],"iteration":724,"passed_time":0.8771221276,"remaining_time":0.3327014967},
{"learn":[3.47820549],"iteration":725,"passed_time":0.8780996241,"remaining_time":0.3314039904},
{"learn":[3.474392283],"iteration":726,"passed_time":0.8789250003,"remaining_time":0.3300502408},
{"learn":[3.472268163],"iteration":727,"passed_time":0.8797131028,"remaining_time":0.3286840164},
{"learn":[3.471209164],"iteration":728,"passed_time":0.8804578737,"remaining_time":0.3273032699},
{"learn":[3.470049971],"iteration":729,"passed_time":0.8812188718,"remaining_time":0.3259302677},
{"learn":[3.469078654],"iteration":730,"passed_time":0.8820032165,"remaining_time":0.3245675311},
{"learn":[3.468643292],"iteration":731,"passed_time":0.8827594266,"remaining_time":0.3231960742},
{"learn":[3.468134848],"iteration":732,"passed_time":0.8834983045,"remaining_time":0.3218199827},
{"learn":[3.467820182],"iteration":733,"passed_time":0.8842306516,"remaining_time":0.3204432606},
{"learn":[3.465776156],"iteration":734,"passed_time":0.8850059881,"remaining_time":0.3190837916},
{"learn":[3.463037608],"iteration":735,"passed_time":0.8857509554,"remaining_time":0.3177150166},
{"learn":[3.45965637],"iteration":736,"passed_time":0.8865164782,"remaining_time":0.3163552697},
{"learn":[3.457275091],"iteration":737,"passed_time":0.8872778809,"remaining_time":0.3149956705},
{"learn":[3.455522955],"iteration":738,"passed_time":0.8880456766,"remaining_time":0.313639948},
{"learn":[3.451270508],"iteration":739,"passed_time":0.888820881,"remaining_time":0.3122884176},
{"learn":[3.450978947],"iteration":740,"passed_time":0.8895641649,"remaining_time":0.3109272857},
{"learn":[3.450608492],"iteration":741,"passed_time":0.8903893421,"remaining_time":0.3095962942},
{"learn":[3.448122004],"iteration":742,"passed_time":0.8917151092,"remaining_time":0.3084398157},
{"learn":[3.445646714],"iteration":743,"passed_time":0.8930566201,"remaining_time":0.3072882994},
{"learn":[3.44411263],"iteration":744,"passed_time":0.8939803824,"remaining_time":0.3059932852},
{"learn":[3.443264164],"iteration":745,"passed_time":0.8947205853,"remaining_time":0.3046367677},
{"learn":[3.439521363],"iteration":746,"passed_time":0.8954678492,"remaining_time":0.3032842916},
{"learn":[3.436809225],"iteration":747,"passed_time":0.8962584265,"remaining_time":0.3019480261},
{"learn":[3.435509465],"iteration":748,"passed_time":0.8970083125,"remaining_time":0.3005995814},
{"learn":[3.434450277],"iteration":749,"passed_time":0.897770871,"remaining_time":0.299256957},
{"learn":[3.431786753],"iteration":750,"passed_time":0.8985265515,"remaining_time":0.297913597},
{"learn":[3.430150302],"iteration":751,"passed_time":0.8992905045,"remaining_time":0.2965745281},
{"learn":[3.42696281],"iteration":752,"passed_time":0.9001030841,"remaining_time":0.2952529373},
{"learn":[3.426870334],"iteration":753,"passed_time":0.9009665909,"remaining_time":0.2939493121},
{"learn":[3.425200309],"iteration":754,"passed_time":0.9017504617,"remaining_time":0.2926210107},
{"learn":[3.423383783],"iteration":755,"passed_time":0.9025316284,"remaining_time":0.2912932769},
{"learn":[3.422752979],"iteration":756,"passed_time":0.9032496904,"remaining_time":0.2899467302},
{"learn":[3.420845924],"iteration":757,"passed_time":0.9040796109,"remaining_time":0.2886375539},
{"learn":[3.418917862],"iteration":758,"passed_time":0.9048994157,"remaining_time":0.2873264284},
{"learn":[3.417095735],"iteration":759,"passed_time":0.9059659413,"remaining_time":0.2860945078},
{"learn":[3.414391848],"iteration":760,"passed_time":0.9070943444,"remaining_time":0.2848824551},
{"learn":[3.41426711],"iteration":761,"passed_time":0.9080968432,"remaining_time":0.2836312975},
{"learn":[3.411976013],"iteration":762,"passed_time":0.9089456388,"remaining_time":0.282333049},
{"learn":[3.408614844],"iteration":763,"passed_time":0.9097183029,"remaining_time":0.2810124601},
{"learn":[3.407906721],"iteration":764,"passed_time":0.910469312,"remaining_time":0.2796866514},
{"learn":[3.407494015],"iteration":765,"passed_time":0.9112451169,"remaining_time":0.2783699182},
{"learn":[3.406287128],"iteration":766,"passed_time":0.9120088492,"remaining_time":0.2770509281},
{"learn":[3.404600442],"iteration":767,"passed_time":0.9127789711,"remaining_time":0.2757353142},
{"learn":[3.404012662],"iteration":768,"passed_time":0.9135124685,"remaining_time":0.2744101173},
{"learn":[3.400398762],"iteration":769,"passed_time":0.9142777471,"remaining_time":0.2730959504},
{"learn":[3.399737714],"iteration":770,"passed_time":0.9151928192,"remaining_time":0.2718276986},
{"learn":[3.399185251],"iteration":771,"passed_time":0.9160187794,"remaining_time":0.2705340437},
{"learn":[3.397245411],"iteration":772,"passed_time":0.9167731323,"remaining_time":0.2692205705},
{"learn":[3.396229831],"iteration":773,"passed_time":0.9175297309,"remaining_time":0.2679091979},
{"learn":[3.394002836],"iteration":774,"passed_time":0.9183247495,"remaining_time":0.2666104111},
{"learn":[3.389617243],"iteration":775,"passed_time":0.919090595,"remaining_time":0.2653045016},
{"learn":[3.385426488],"iteration":776,"passed_time":0.9199324834,"remaining_time":0.2640218067},
{"learn":[3.385072258],"iteration":777,"passed_time":0.9208196071,"remaining_time":0.2627531527},
{"learn":[3.383842366],"iteration":778,"passed_time":0.9220361197,"remaining_time":0.2615789248},
{"learn":[3.380110746],"iteration":779,"passed_time":0.9230880461,"remaining_time":0.2603581669},
{"learn":[3.378595218],"iteration":780,"passed_time":0.9238325677,"remaining_time":0.2590516419},
{"learn":[3.377371219],"iteration":781,"passed_time":0.9245826522,"remaining_time":0.2577481051},
{"learn":[3.375814782],"iteration":782,"passed_time":0.9253405096,"remaining_time":0.2564481361},
{"learn":[3.374195887],"iteration":783,"passed_time":0.9261037173,"remaining_time":0.2551510242},
{"learn":[3.373704309],"iteration":784,"passed_time":0.9268472641,"remaining_time":0.2538498876},
{"learn":[3.372971757],"iteration":785,"passed_time":0.9275957219,"remaining_time":0.252551507},
{"learn":[3.371565136],"iteration":786,"passed_time":0.9283613759,"remaining_time":0.251259178},
{"learn":[3.3700309],"iteration":787,"passed_time":0.9291403079,"remaining_time":0.249971758},
{"learn":[3.368186663],"iteration":788,"passed_time":0.9298889682,"remaining_time":0.2486775314},
{"learn":[3.366710398],"iteration":789,"passed_time":0.9306653444,"remaining_time":0.2473920536},
{"learn":[3.364598042],"iteration":790,"passed_time":0.9315486761,"remaining_time":0.246136123},
{"learn":[3.36348442],"iteration":791,"passed_time":0.9323037566,"remaining_time":0.2448474512},
{"learn":[3.362001759],"iteration":792,"passed_time":0.9330590155,"remaining_time":0.2435601718},
{"learn":[3.361580401],"iteration":793,"passed_time":0.9337981335,"remaining_time":0.2422700447},
{"learn":[3.359543675],"iteration":794,"passed_time":0.934612286,"remaining_time":0.2410006524},
{"learn":[3.35766119],"iteration":795,"passed_time":0.9355974595,"remaining_time":0.2397762333},
{"learn":[3.354592969],"iteration":796,"passed_time":0.9365128332,"remaining_time":0.2385346363},
{"learn":[3.350985986],"iteration":797,"passed_time":0.9374452598,"remaining_time":0.2372981735},
{"learn":[3.349589624],"iteration":798,"passed_time":0.9382248757,"remaining_time":0.2360240301},
{"learn":[3.349110856],"iteration":799,"passed_time":0.9391032566,"remaining_time":0.2347758141},
{"learn":[3.345315441],"iteration":800,"passed_time":0.9398817142,"remaining_time":0.2335036968},
{"learn":[3.34397474],"iteration":801,"passed_time":0.9406630915,"remaining_time":0.2322335313},
{"learn":[3.343800902],"iteration":802,"passed_time":0.941408589,"remaining_time":0.2309557809},
{"learn":[3.342329465],"iteration":803,"passed_time":0.9421421738,"remaining_time":0.2296764503},
{"learn":[3.34220347],"iteration":804,"passed_time":0.9428581217,"remaining_time":0.2283942034},
{"learn":[3.341279219],"iteration":805,"passed_time":0.9436026122,"remaining_time":0.2271202317},
{"learn":[3.337329521],"iteration":806,"passed_time":0.9444012977,"remaining_time":0.2258605334},
{"learn":[3.336708453],"iteration":807,"passed_time":0.9452795137,"remaining_time":0.2246208745},
{"learn":[3.333252703],"iteration":808,"passed_time":0.946049831,"remaining_time":0.223356635},
{"learn":[3.332186769],"iteration":809,"passed_time":0.9468440677,"remaining_time":0.2220992258},
{"learn":[3.330594851],"iteration":810,"passed_time":0.9475974879,"remaining_time":0.2208334466},
{"learn":[3.327867442],"iteration":811,"passed_time":0.9483386251,"remaining_time":0.2195660856},
{"learn":[3.327563111],"iteration":812,"passed_time":0.94912952,"remaining_time":0.218311464},
{"learn":[3.326308994],"iteration":813,"passed_time":0.9501068527,"remaining_time":0.217100583},
{"learn":[3.326249879],"iteration":814,"passed_time":0.9510292425,"remaining_time":0.2158778035},
{"learn":[3.322336238],"iteration":815,"passed_time":0.9520506897,"remaining_time":0.2146780967},
{"learn":[3.320491154],"iteration":816,"passed_time":0.9528261589,"remaining_time":0.2134237296},
{"learn":[3.320434271],"iteration":817,"passed_time":0.9535635352,"remaining_time":0.212162058},
{"learn":[3.319609638],"iteration":818,"passed_time":0.9543307741,"remaining_time":0.2109082663},
{"learn":[3.316182682],"iteration":819,"passed_time":0.9551102755,"remaining_time":0.2096583532},
{"learn":[3.313126612],"iteration":820,"passed_time":0.9558717294,"remaining_time":0.2084056511},
{"learn":[3.311222803],"iteration":821,"passed_time":0.9566494705,"remaining_time":0.2071576712},
{"learn":[3.309627335],"iteration":822,"passed_time":0.9574142109,"remaining_time":0.2059080381},
{"learn":[3.307974895],"iteration":823,"passed_time":0.9581920268,"remaining_time":0.2046623747},
{"learn":[3.307321505],"iteration":824,"passed_time":0.9589583291,"remaining_time":0.2034154031},
{"learn":[3.306759087],"iteration":825,"passed_time":0.9597171046,"remaining_time":0.2021680099},
{"learn":[3.30484037],"iteration":826,"passed_time":0.9604774505,"remaining_time":0.2009221269},
{"learn":[3.30201994],"iteration":827,"passed_time":0.96123033,"remaining_time":0.1996758656},
{"learn":[3.299302297],"iteration":828,"passed_time":0.9620177701,"remaining_time":0.1984379236},
{"learn":[3.298132671],"iteration":829,"passed_time":0.9627595932,"remaining_time":0.1971917239},
{"learn":[3.296976183],"iteration":830,"passed_time":0.9635248361,"remaining_time":0.195951501},
{"learn":[3.293144745],"iteration":831,"passed_time":0.9644572633,"remaining_time":0.1947461782},
{"learn":[3.290284404],"iteration":832,"passed_time":0.9655732914,"remaining_time":0.1935783189},
{"learn":[3.288285745],"iteration":833,"passed_time":0.9665644106,"remaining_time":0.192385722},
{"learn":[3.286662667],"iteration":834,"passed_time":0.9674300079,"remaining_time":0.191168804},
{"learn":[3.285692682],"iteration":835,"passed_time":0.9682385744,"remaining_time":0.1899415385},
{"learn":[3.284565611],"iteration":836,"passed_time":0.969022008,"remaining_time":0.1887103791},
{"learn":[3.283897383],"iteration":837,"passed_time":0.9698276297,"remaining_time":0.1874845776},
{"learn":[3.280712855],"iteration":838,"passed_time":0.9705783906,"remaining_time":0.1862492502},
{"learn":[3.280468341],"iteration":839,"passed_time":0.9713059241,"remaining_time":0.1850106522},
{"learn":[3.277814895],"iteration":840,"passed_time":0.9720763419,"remaining_time":0.1837813774},
{"learn":[3.276316385],"iteration":841,"passed_time":0.9729302215,"remaining_time":0.1825688539},
{"learn":[3.27557063],"iteration":842,"passed_time":0.9736892181,"remaining_time":0.1813395104},
{"learn":[3.27499628],"iteration":843,"passed_time":0.9744284261,"remaining_time":0.1801076238},
{"learn":[3.273569958],"iteration":844,"passed_time":0.975180094,"remaining_time":0.1788791888},
{"learn":[3.269665595],"iteration":845,"passed_time":0.9759342861,"remaining_time":0.1776523405},
{"learn":[3.267984685],"iteration":846,"passed_time":0.9767177885,"remaining_time":0.1764319028},
{"learn":[3.267702508],"iteration":847,"passed_time":0.9774576879,"remaining_time":0.1752046799},
{"learn":[3.266671924],"iteration":848,"passed_time":0.9782203529,"remaining_time":0.1739826541},
{"learn":[3.265359825],"iteration":849,"passed_time":0.9790759642,"remaining_time":0.1727781113},
{"learn":[3.2618983],"iteration":850,"passed_time":0.9800716624,"remaining_time":0.1715989162},
{"learn":[3.260456253],"iteration":851,"passed_time":0.9809935241,"remaining_time":0.1704073258},
{"learn":[3.258389147],"iteration":852,"passed_time":0.9818987695,"remaining_time":0.1692135042},
{"learn":[3.258108469],"iteration":853,"passed_time":0.9826488193,"remaining_time":0.1679938263},
{"learn":[3.256424936],"iteration":854,"passed_time":0.9834790298,"remaining_time":0.1667888413},
{"learn":[3.254817983],"iteration":855,"passed_time":0.9843304576,"remaining_time":0.1655883013},
{"learn":[3.253898449],"iteration":856,"passed_time":0.9852039313,"remaining_time":0.1643922546},
{"learn":[3.253023652],"iteration":857,"passed_time":0.9861085591,"remaining_time":0.1632021158},
{"learn":[3.252845542],"iteration":858,"passed_time":0.9870242263,"remaining_time":0.1620144539},
{"learn":[3.252316026],"iteration":859,"passed_time":0.9878205741,"remaining_time":0.1608080004},
{"learn":[3.24975301],"iteration":860,"passed_time":0.9886357291,"remaining_time":0.1596055358},
{"learn":[3.249151075],"iteration":861,"passed_time":0.9894180406,"remaining_time":0.1583987118},
{"learn":[3.246257135],"iteration":862,"passed_time":0.9902058446,"remaining_time":0.1571937436},
{"learn":[3.243826471],"iteration":863,"passed_time":0.9910067009,"remaining_time":0.1559917955},
{"learn":[3.243190653],"iteration":864,"passed_time":0.9918660796,"remaining_time":0.1547999084},
{"learn":[3.24008797],"iteration":865,"passed_time":0.9926613595,"remaining_time":0.1535988709},
{"learn":[3.240036811],"iteration":866,"passed_time":0.9934023278,"remaining_time":0.1523904378},
{"learn":[3.238676314],"iteration":867,"passed_time":0.9942934771,"remaining_time":0.1512059205},
{"learn":[3.237848782],"iteration":868,"passed_time":0.9953820471,"remaining_time":0.1500518391},
{"learn":[3.236405498],"iteration":869,"passed_time":0.9964617703,"remaining_time":0.1488965864},
{"learn":[3.233378068],"iteration":870,"passed_time":0.997292324,"remaining_time":0.1477046037},
{"learn":[3.233169169],"iteration":871,"passed_time":0.9980563232,"remaining_time":0.1465036805},
{"learn":[3.232434885],"iteration":872,"passed_time":0.9989897971,"remaining_time":0.1453284126},
{"learn":[3.229978115],"iteration":873,"passed_time":0.9997723287,"remaining_time":0.1441319375},
{"learn":[3.229648848],"iteration":874,"passed_time":1.000538557,"remaining_time":0.1429340795},
{"learn":[3.227208761],"iteration":875,"passed_time":1.001326297,"remaining_time":0.1417402521},
{"learn":[3.226258869],"iteration":876,"passed_time":1.002133433,"remaining_time":0.1405500709},
{"learn":[3.225331995],"iteration":877,"passed_time":1.003042044,"remaining_time":0.1393748626},
{"learn":[3.221968268],"iteration":878,"passed_time":1.003823825,"remaining_time":0.1381828019},
{"learn":[3.221166317],"iteration":879,"passed_time":1.00459269,"remaining_time":0.1369899122},
{"learn":[3.220047503],"iteration":880,"passed_time":1.005355116,"remaining_time":0.1357971155},
{"learn":[3.21982781],"iteration":881,"passed_time":1.006102192,"remaining_time":0.1346032411},
{"learn":[3.216693405],"iteration":882,"passed_time":1.0068762,"remaining_time":0.1334139472},
{"learn":[3.214798761],"iteration":883,"passed_time":1.007647802,"remaining_time":0.1322252771},
{"learn":[3.214395085],"iteration":884,"passed_time":1.008388075,"remaining_time":0.1310334787},
{"learn":[3.213470696],"iteration":885,"passed_time":1.009253588,"remaining_time":0.1298588138},
{"learn":[3.211595017],"iteration":886,"passed_time":1.010283302,"remaining_time":0.1287057645},
{"learn":[3.210965255],"iteration":887,"passed_time":1.011257057,"remaining_time":0.1275459351},
{"learn":[3.209413583],"iteration":888,"passed_time":1.012029531,"remaining_time":0.1263613925},
{"learn":[3.208331683],"iteration":889,"passed_time":1.012784308,"remaining_time":0.1251755886},
{"learn":[3.207110711],"iteration":890,"passed_time":1.013631265,"remaining_time":0.124002029},
{"learn":[3.204519413],"iteration":891,"passed_time":1.014394604,"remaining_time":0.1228190776},
{"learn":[3.201421296],"iteration":892,"passed_time":1.015151384,"remaining_time":0.1216362801},
{"learn":[3.200691259],"iteration":893,"passed_time":1.015908136,"remaining_time":0.1204544322},
{"learn":[3.200485067],"iteration":894,"passed_time":1.016671139,"remaining_time":0.1192742677},
{"learn":[3.197467568],"iteration":895,"passed_time":1.017451036,"remaining_time":0.1180969952},
{"learn":[3.195838544],"iteration":896,"passed_time":1.018270266,"remaining_time":0.1169251253},
{"learn":[3.195671746],"iteration":897,"passed_time":1.019025129,"remaining_time":0.1157467296},
{"learn":[3.194213094],"iteration":898,"passed_time":1.019988698,"remaining_time":0.1145927235},
{"learn":[3.192884691],"iteration":899,"passed_time":1.020930206,"remaining_time":0.1134366896},
{"learn":[3.188364239],"iteration":900,"passed_time":1.021790063,"remaining_time":0.1122721601},
{"learn":[3.185219478],"iteration":901,"passed_time":1.022794362,"remaining_time":0.1111239995},
{"learn":[3.184120387],"iteration":902,"passed_time":1.023755113,"remaining_time":0.1099714794},
{"learn":[3.183725321],"iteration":903,"passed_time":1.024847905,"remaining_time":0.1088334058},
{"learn":[3.181264554],"iteration":904,"passed_time":1.025956493,"remaining_time":0.1076970904},
{"learn":[3.180741589],"iteration":905,"passed_time":1.026983959,"remaining_time":0.1065524196},
{"learn":[3.179782639],"iteration":906,"passed_time":1.027973469,"remaining_time":0.1054041154},
{"learn":[3.176377564],"iteration":907,"passed_time":1.028963078,"remaining_time":0.1042561709},
{"learn":[3.174078182],"iteration":908,"passed_time":1.030146309,"remaining_time":0.1031279583},
{"learn":[3.171242379],"iteration":909,"passed_time":1.031174224,"remaining_time":0.1019842639},
{"learn":[3.170421012],"iteration":910,"passed_time":1.032174482,"remaining_time":0.1008381218},
{"learn":[3.170087224],"iteration":911,"passed_time":1.033201322,"remaining_time":0.09969486445},
{"learn":[3.167303059],"iteration":912,"passed_time":1.034106534,"remaining_time":0.09854027216},
{"learn":[3.16705966],"iteration":913,"passed_time":1.035004943,"remaining_time":0.09738558549},
{"learn":[3.165667683],"iteration":914,"passed_time":1.035902164,"remaining_time":0.09623134858},
{"learn":[3.164689733],"iteration":915,"passed_time":1.036755675,"remaining_time":0.09507366455},
{"learn":[3.163311455],"iteration":916,"passed_time":1.037594096,"remaining_time":0.09391527804},
{"learn":[3.159425016],"iteration":917,"passed_time":1.038440206,"remaining_time":0.09275827545},
{"learn":[3.159327058],"iteration":918,"passed_time":1.039668418,"remaining_time":0.09163562769},
{"learn":[3.15819426],"iteration":919,"passed_time":1.040905755,"remaining_time":0.0905135439},
{"learn":[3.157086603],"iteration":920,"passed_time":1.041953514,"remaining_time":0.08937494853},
{"learn":[3.153354154],"iteration":921,"passed_time":1.04275399,"remaining_time":0.08821563038},
{"learn":[3.153261317],"iteration":922,"passed_time":1.043590766,"remaining_time":0.08706011809},
{"learn":[3.153168454],"iteration":923,"passed_time":1.044386993,"remaining_time":0.08590196045},
{"learn":[3.152080399],"iteration":924,"passed_time":1.045232813,"remaining_time":0.08474860642},
{"learn":[3.151635144],"iteration":925,"passed_time":1.046027327,"remaining_time":0.08359181664},
{"learn":[3.147762655],"iteration":926,"passed_time":1.046869426,"remaining_time":0.08243955568},
{"learn":[3.147172317],"iteration":927,"passed_time":1.047707736,"remaining_time":0.08128766915},
{"learn":[3.146254125],"iteration":928,"passed_time":1.048610888,"remaining_time":0.08014141341},
{"learn":[3.144869828],"iteration":929,"passed_time":1.049444906,"remaining_time":0.07899047678},
{"learn":[3.143466218],"iteration":930,"passed_time":1.050377267,"remaining_time":0.07784750955},
{"learn":[3.141919643],"iteration":931,"passed_time":1.051199582,"remaining_time":0.07669696524},
{"learn":[3.141054135],"iteration":932,"passed_time":1.052079907,"remaining_time":0.07555129021},
{"learn":[3.139390417],"iteration":933,"passed_time":1.052958341,"remaining_time":0.0744060498},
{"learn":[3.139025283],"iteration":934,"passed_time":1.053879196,"remaining_time":0.07326432912},
{"learn":[3.137824183],"iteration":935,"passed_time":1.055054159,"remaining_time":0.07214045533},
{"learn":[3.135620453],"iteration":936,"passed_time":1.056344443,"remaining_time":0.07102422616},
{"learn":[3.13443178],"iteration":937,"passed_time":1.057323371,"remaining_time":0.06988704585},
{"learn":[3.132765713],"iteration":938,"passed_time":1.058247147,"remaining_time":0.06874661977},
{"learn":[3.131434124],"iteration":939,"passed_time":1.059228377,"remaining_time":0.06761032191},
{"learn":[3.128384262],"iteration":940,"passed_time":1.060059513,"remaining_time":0.06646494291},
{"learn":[3.128120455],"iteration":941,"passed_time":1.060853002,"remaining_time":0.06531791305},
{"learn":[3.126314615],"iteration":942,"passed_time":1.061674887,"remaining_time":0.0641733495},
{"learn":[3.125409666],"iteration":943,"passed_time":1.062460438,"remaining_time":0.06302731409},
{"learn":[3.123072589],"iteration":944,"passed_time":1.063235274,"remaining_time":0.06188141804},
{"learn":[3.122921099],"iteration":945,"passed_time":1.063980399,"remaining_time":0.0607346105},
{"learn":[3.122182662],"iteration":946,"passed_time":1.064760402,"remaining_time":0.05959060329},
{"learn":[3.120040951],"iteration":947,"passed_time":1.065562678,"remaining_time":0.05844858569},
{"learn":[3.118767799],"iteration":948,"passed_time":1.066323693,"remaining_time":0.05730506674},
{"learn":[3.118203218],"iteration":949,"passed_time":1.067078616,"remaining_time":0.0561620324},
{"learn":[3.116343362],"iteration":950,"passed_time":1.067837868,"remaining_time":0.05502003739},
{"learn":[3.11480829],"iteration":951,"passed_time":1.068706401,"remaining_time":0.05388435635},
{"learn":[3.112607903],"iteration":952,"passed_time":1.06980363,"remaining_time":0.0527605148},
{"learn":[3.111661241],"iteration":953,"passed_time":1.0707706,"remaining_time":0.0516304482},
{"learn":[3.110249676],"iteration":954,"passed_time":1.071618549,"remaining_time":0.05049511487},
{"learn":[3.107333579],"iteration":955,"passed_time":1.072396578,"remaining_time":0.0493571647},
{"learn":[3.107149851],"iteration":956,"passed_time":1.073137888,"remaining_time":0.0482183168},
{"learn":[3.106867336],"iteration":957,"passed_time":1.07393664,"remaining_time":0.04708281722},
{"learn":[3.10364681],"iteration":958,"passed_time":1.074717257,"remaining_time":0.04594724455},
{"learn":[3.102703811],"iteration":959,"passed_time":1.075556755,"remaining_time":0.04481486478},
{"learn":[3.101469264],"iteration":960,"passed_time":1.076368737,"remaining_time":0.0436819779},
{"learn":[3.09863569],"iteration":961,"passed_time":1.077188273,"remaining_time":0.04255005654},
{"learn":[3.09645939],"iteration":962,"passed_time":1.077952426,"remaining_time":0.04141665603},
{"learn":[3.096240186],"iteration":963,"passed_time":1.078712999,"remaining_time":0.04028388794},
{"learn":[3.094838828],"iteration":964,"passed_time":1.079480977,"remaining_time":0.03915215979},
{"learn":[3.094176802],"iteration":965,"passed_time":1.080284656,"remaining_time":0.03802244131},
{"learn":[3.093182279],"iteration":966,"passed_time":1.081023116,"remaining_time":0.03689117148},
{"learn":[3.090150687],"iteration":967,"passed_time":1.081768373,"remaining_time":0.03576093795},
{"learn":[3.088612829],"iteration":968,"passed_time":1.0825093,"remaining_time":0.03463136046},
{"learn":[3.087153684],"iteration":969,"passed_time":1.083455707,"remaining_time":0.0335089394},
{"learn":[3.085866843],"iteration":970,"passed_time":1.084658218,"remaining_time":0.03239452968},
{"learn":[3.082669094],"iteration":971,"passed_time":1.085761499,"remaining_time":0.03127708022},
{"learn":[3.081047548],"iteration":972,"passed_time":1.086618829,"remaining_time":0.03015283494},
{"learn":[3.079684322],"iteration":973,"passed_time":1.087436075,"remaining_time":0.02902806772},
{"learn":[3.07613431],"iteration":974,"passed_time":1.088176253,"remaining_time":0.0279019552},
{"learn":[3.074005935],"iteration":975,"passed_time":1.088959567,"remaining_time":0.02677769426},
{"learn":[3.072988853],"iteration":976,"passed_time":1.089727755,"remaining_time":0.02565377519},
{"learn":[3.072344268],"iteration":977,"passed_time":1.090455752,"remaining_time":0.02452967949},
{"learn":[3.070654438],"iteration":978,"passed_time":1.091206991,"remaining_time":0.02340689153},
{"learn":[3.069724506],"iteration":979,"passed_time":1.092009965,"remaining_time":0.02228591766},
{"learn":[3.067763166],"iteration":980,"passed_time":1.092810498,"remaining_time":0.02116554482},
{"learn":[3.066737893],"iteration":981,"passed_time":1.093573633,"remaining_time":0.02004513787},
{"learn":[3.065248174],"iteration":982,"passed_time":1.094345644,"remaining_time":0.01892561134},
{"learn":[3.063186837],"iteration":983,"passed_time":1.095097252,"remaining_time":0.01780645939},
{"learn":[3.062880371],"iteration":984,"passed_time":1.09585359,"remaining_time":0.01668812574},
{"learn":[3.061288645],"iteration":985,"passed_time":1.096780269,"remaining_time":0.01557294499},
{"learn":[3.059970575],"iteration":986,"passed_time":1.097599893,"remaining_time":0.01445673617},
{"learn":[3.059576341],"iteration":987,"passed_time":1.098517412,"remaining_time":0.01334231674},
{"learn":[3.058175919],"iteration":988,"passed_time":1.099491881,"remaining_time":0.01222892891},
{"learn":[3.056830702],"iteration":989,"passed_time":1.100480147,"remaining_time":0.01111596108},
{"learn":[3.056336579],"iteration":990,"passed_time":1.101241658,"remaining_time":0.0100011856},
{"learn":[3.055810414],"iteration":991,"passed_time":1.10201613,"remaining_time":0.008887226856},
{"learn":[3.055476518],"iteration":992,"passed_time":1.102778269,"remaining_time":0.007773864934},
{"learn":[3.053331734],"iteration":993,"passed_time":1.103595213,"remaining_time":0.006661540521},
{"learn":[3.050890374],"iteration":994,"passed_time":1.104356801,"remaining_time":0.005549531661},
{"learn":[3.04972623],"iteration":995,"passed_time":1.105125734,"remaining_time":0.00443825596},
{"learn":[3.047217327],"iteration":996,"passed_time":1.105896801,"remaining_time":0.003327673422},
{"learn":[3.047155483],"iteration":997,"passed_time":1.106631507,"remaining_time":0.00221769841},
{"learn":[3.04430671],"iteration":998,"passed_time":1.107390022,"remaining_time":0.001108498521},
{"learn":[3.042664195],"iteration":999,"passed_time":1.108304438,"remaining_time":0}
]}